{
  "model": [
    {
      "productVisible": true,
      "_links": {
        "look": {
          "href": "/api/catalog/jpn-jp/skus/nvsku2680006v/look"
        },
        "parent": {
          "href": "/api/catalog/jpn-jp/product/nvprod2940006v"
        },
        "self": {
          "href": "/api/catalog/jpn-jp/product/nvsku2680006v"
        },
        "perso-details": {
          "href": "/api/catalog/jpn-jp/skus/nvsku2680006v/perso-detail"
        },
        "/api/rels/jpn-jp/add-to-cart-base/nvprod2940006v/nvsku2680006v/1": {
          "name": "add-to-cart",
          "href": "/api/cart/jpn-jp"
        }
      },
      "@type": "ProductModel",
      "name": "LVxNBA II - Look 06",
      "image": [
        {
          "contentUrl": "https://jp.louisvuitton.com/images/is/image/lv/1/PP_VP_L/louis-vuitton--Men_NBA_drop2_LOOK06_VISUAL4.jpg?wid={IMG_WIDTH}&hei={IMG_HEIGHT}",
          "@type": "ImageObject",
          "name": "drop2",
          "@context": "http://schema.org"
        }
      ],
      "url": "/jpn-jp/products/lvxnba-ii-look-06-nvprod2940006v",
      "highEndTemplate": false,
      "productId": "nvprod2940006v",
      "additionalProperty": [
        {
          "@type": "PropertyValue",
          "name": "activateEngraving",
          "value": false
        },
        {
          "@type": "PropertyValue",
          "name": "sellable",
          "value": false
        },
        {
          "@type": "PropertyValue",
          "name": "cscSellable",
          "value": true
        },
        {
          "@type": "PropertyValue",
          "name": "mom",
          "value": false
        },
        {
          "@type": "PropertyValue",
          "name": "locateInStore",
          "value": true
        },
        {
          "@type": "PropertyValue",
          "name": "backOrderDisclaimer",
          "value": true
        },
        {
          "@type": "PropertyValue",
          "name": "backOrderFullDeposit",
          "value": false
        },
        {
          "@type": "PropertyValue",
          "name": "tryOnEnabled",
          "value": false
        },
        {
          "@type": "PropertyValue",
          "name": "isBundle",
          "value": false
        },
        {
          "@type": "PropertyValue",
          "name": "360ViewEnabled",
          "value": false
        }
      ],
      "category": [
        {
          "@type": "Thing",
          "url": "/jpn-jp/men/_/N-1cyoz77",
          "alternateName": "men",
          "name": "メンズ",
          "identifier": "homme"
        },
        {
          "@type": "Thing",
          "url": "/jpn-jp/men/ready-to-wear/_/N-1lpb5id",
          "alternateName": "ready-to-wear",
          "name": "プレタポルテ（洋服）",
          "identifier": "m-readytowear"
        },
        {
          "@type": "Thing",
          "url": "/jpn-jp/men/ready-to-wear/view-by-look/_/N-1ui6ldg",
          "alternateName": "view-by-look",
          "name": "ルックブック",
          "identifier": "nvcat450010v"
        }
      ],
      "disclaimers": {
        "value": "shipping_warning_bo",
        "popInContent": "global_backorder_info_popin_content",
        "popInTitle": "global_backorder_info_popin_title"
      },
      "@context": "http://schema.org",
      "identifier": "nvsku2680006v"
    }
  ],
  "readyToWearSKUs": [
    {
      "productVisible": true,
      "_links": {
        "look": {
          "href": "/api/catalog/jpn-jp/skus/1A8WQE/look"
        },
        "parent": {
          "href": "/api/catalog/jpn-jp/product/nvprod2790138v"
        },
        "self": {
          "href": "/api/catalog/jpn-jp/product/1A8WQE"
        },
        "perso-details": {
          "href": "/api/catalog/jpn-jp/skus/1A8WQE/perso-detail"
        },
        "/api/rels/jpn-jp/add-to-cart-base/nvprod2790138v/1A8WQE/1": {
          "name": "add-to-cart",
          "href": "/api/cart/jpn-jp"
        }
      },
      "macroColor": "ブラック",
      "@type": "ProductModel",
      "name": "NBAジャージージャケット",
      "offers": {
        "priceSpecification": {
          "priceCurrency": "JPY",
          "price": 410300
        },
        "@type": "Offer",
        "price": "¥410,300"
      },
      "disambiguatingDescription": "今シーズンならではの「NBA」のテーマにフォーマルなひねりを加えた、ボクシーなシルエットのジャケット。厚手のダブルフェイスのジャージー素材をレギュラーフィットに仕立て、サイドベンツ、フラップポケット、胸元にはウェルトポケットを添えました。メタリックなLV ボタン、NBAのロゴをエンボス加工したレザーパッチ、内側にあしらったジャカード織りのNBA ストラテジック モノグラム･フラワー パターンが魅力です。<p>ご不明な点がございましたら、クライアントサービスまでお気軽にお問合せください。専任のクライアントアドバイザーが、素材やサイズなどの製品詳細、モデル着用イメージや関連アイテムのご案内など、お客様のご要望に合わせたスタイリング・アドバイスをご提供いたします。</p><p>また、サイズ違いなどによる返品・交換のご相談も承ります。詳細は<a href=\"https://jp.louisvuitton.com/jpn-jp/legal-privacy\"><b>こちら。</b></a></p>",
      "image": [
        {
          "contentUrl": "https://jp.louisvuitton.com/images/is/image/lv/1/PP_VP_L/louis-vuitton-nbaジャージージャケット--HLJ01WET2900_PM2_Front view.jpg?wid={IMG_WIDTH}&hei={IMG_HEIGHT}",
          "@type": "ImageObject",
          "name": "Front view",
          "@context": "http://schema.org"
        },
        {
          "playerType": "freecaster",
          "contentUrl": "https://player.louisvuitton.com/embed/1400565",
          "@type": "ImageObject",
          "name": "freecaster media",
          "@context": "http://schema.org"
        },
        {
          "contentUrl": "https://jp.louisvuitton.com/images/is/image/lv/1/PP_VP_L/louis-vuitton-nbaジャージージャケット--HLJ01WET2900_PM1_Worn view.jpg?wid={IMG_WIDTH}&hei={IMG_HEIGHT}",
          "@type": "ImageObject",
          "name": "Worn view",
          "@context": "http://schema.org"
        },
        {
          "contentUrl": "https://jp.louisvuitton.com/images/is/image/lv/1/PP_VP_L/louis-vuitton-nbaジャージージャケット--HLJ01WET2900_PM1_Closeup view.jpg?wid={IMG_WIDTH}&hei={IMG_HEIGHT}",
          "@type": "ImageObject",
          "name": "Closeup view",
          "@context": "http://schema.org"
        },
        {
          "contentUrl": "https://jp.louisvuitton.com/images/is/image/lv/1/PP_VP_L/louis-vuitton-nbaジャージージャケット--HLJ01WET2900_PM1_Side view.jpg?wid={IMG_WIDTH}&hei={IMG_HEIGHT}",
          "@type": "ImageObject",
          "name": "Side view",
          "@context": "http://schema.org"
        },
        {
          "contentUrl": "https://jp.louisvuitton.com/images/is/image/lv/1/PP_VP_L/louis-vuitton-nbaジャージージャケット--HLJ01WET2900_PM1_Detail view.jpg?wid={IMG_WIDTH}&hei={IMG_HEIGHT}",
          "@type": "ImageObject",
          "name": "Detail view",
          "@context": "http://schema.org"
        }
      ],
      "url": "/jpn-jp/products/lvxnba-jersey-jacket-nvprod2790138v",
      "highEndTemplate": false,
      "sizeDisplayName": "50",
      "productId": "nvprod2790138v",
      "additionalProperty": [
        {
          "@type": "PropertyValue",
          "name": "colorIconURL",
          "value": "https://jp.louisvuitton.com/images/is/image/lv/1/LV/louis-vuitton--MKC-RTW-900_noir.jpg"
        },
        {
          "@type": "PropertyValue",
          "name": "detailedDescription",
          "value": "<ul><li>本体：ウール 59%、コットン 37%、ナイロン 4%</li><li>レギュラーフィット</li><li>モデル：胸囲 92cm、身長 185cm</li><li>モデル着用48サイズ</li><li>イタリア製</li><li>REF：HLJ01WET2</li></ul>"
        },
        {
          "@type": "PropertyValue",
          "name": "activateEngraving",
          "value": false
        },
        {
          "@type": "PropertyValue",
          "name": "sellable",
          "value": true
        },
        {
          "@type": "PropertyValue",
          "name": "cscSellable",
          "value": true
        },
        {
          "@type": "PropertyValue",
          "name": "mom",
          "value": false
        },
        {
          "@type": "PropertyValue",
          "name": "locateInStore",
          "value": true
        },
        {
          "@type": "PropertyValue",
          "name": "materialGroupCode",
          "value": "Z05"
        },
        {
          "@type": "PropertyValue",
          "name": "filterCategories",
          "value": "Ready_To_Wear_Men"
        },
        {
          "@type": "PropertyValue",
          "name": "backOrderDisclaimer",
          "value": true
        },
        {
          "@type": "PropertyValue",
          "name": "backOrderFullDeposit",
          "value": false
        },
        {
          "@type": "PropertyValue",
          "name": "tryOnEnabled",
          "value": false
        },
        {
          "@type": "PropertyValue",
          "name": "isBundle",
          "value": false
        },
        {
          "@type": "PropertyValue",
          "name": "360ViewEnabled",
          "value": false
        }
      ],
      "category": [
        {
          "@type": "Thing",
          "url": "/jpn-jp/men/_/N-1cyoz77",
          "alternateName": "men",
          "name": "メンズ",
          "identifier": "homme"
        },
        {
          "@type": "Thing",
          "url": "/jpn-jp/men/ready-to-wear/_/N-1lpb5id",
          "alternateName": "ready-to-wear",
          "name": "プレタポルテ（洋服）",
          "identifier": "m-readytowear"
        },
        {
          "@type": "Thing",
          "url": "/jpn-jp/men/ready-to-wear/blazers-and-jackets/_/N-hdst0k",
          "alternateName": "blazers-and-jackets",
          "name": "メンズ ブレザー＆ジャケット",
          "identifier": "m-jackets-mrtw"
        }
      ],
      "disclaimers": {
        "value": "shipping_warning_bo",
        "popInContent": "global_backorder_info_popin_content",
        "popInTitle": "global_backorder_info_popin_title"
      },
      "color": "ノワール",
      "@context": "http://schema.org",
      "identifier": "1A8WQE"
    },
    {
      "productVisible": true,
      "_links": {
        "look": {
          "href": "/api/catalog/jpn-jp/skus/1A8WXA/look"
        },
        "parent": {
          "href": "/api/catalog/jpn-jp/product/nvprod2800003v"
        },
        "self": {
          "href": "/api/catalog/jpn-jp/product/1A8WXA"
        },
        "perso-details": {
          "href": "/api/catalog/jpn-jp/skus/1A8WXA/perso-detail"
        },
        "/api/rels/jpn-jp/add-to-cart-base/nvprod2800003v/1A8WXA/1": {
          "name": "add-to-cart",
          "href": "/api/cart/jpn-jp"
        }
      },
      "macroColor": "ブラック",
      "@type": "ProductModel",
      "name": "NBAジャージークラシックパンツ",
      "offers": {
        "priceSpecification": {
          "priceCurrency": "JPY",
          "price": 146300
        },
        "@type": "Offer",
        "price": "¥146,300"
      },
      "disambiguatingDescription": "コレクションの「NBA」のテーマに、フォーマルな雰囲気をプラスしたクラシカルなパンツ。コットンと責任ある調達によるウールの混紡素材を、レギュラーフィットのストレートカットに仕立てた1着です。左足にはNBAのロゴをエンボス加工で施したレザーパッチをあしらい、ベルトループにはLV メダリオンを添えました。半分隠れたドローストリングと、背面の玉縁ポケットがスタイルを完成させます。<p>ご不明な点がございましたら、クライアントサービスまでお気軽にお問合せください。専任のクライアントアドバイザーが、素材やサイズなどの製品詳細、モデル着用イメージや関連アイテムのご案内など、お客様のご要望に合わせたスタイリング・アドバイスをご提供いたします。</p><p>また、サイズ違いなどによる返品・交換のご相談も承ります。詳細は<a href=\"https://jp.louisvuitton.com/jpn-jp/legal-privacy\"><b>こちら。</b></a></p>",
      "image": [
        {
          "contentUrl": "https://jp.louisvuitton.com/images/is/image/lv/1/PP_VP_L/louis-vuitton-nbaジャージークラシックパンツ--HLP10WET2900_PM2_Front view.jpg?wid={IMG_WIDTH}&hei={IMG_HEIGHT}",
          "@type": "ImageObject",
          "name": "Front view",
          "@context": "http://schema.org"
        },
        {
          "playerType": "freecaster",
          "contentUrl": "https://player.louisvuitton.com/embed/1400609",
          "@type": "ImageObject",
          "name": "freecaster media",
          "@context": "http://schema.org"
        },
        {
          "contentUrl": "https://jp.louisvuitton.com/images/is/image/lv/1/PP_VP_L/louis-vuitton-nbaジャージークラシックパンツ--HLP10WET2900_PM1_Worn view.jpg?wid={IMG_WIDTH}&hei={IMG_HEIGHT}",
          "@type": "ImageObject",
          "name": "Worn view",
          "@context": "http://schema.org"
        },
        {
          "contentUrl": "https://jp.louisvuitton.com/images/is/image/lv/1/PP_VP_L/louis-vuitton-nbaジャージークラシックパンツ--HLP10WET2900_PM1_Closeup view.jpg?wid={IMG_WIDTH}&hei={IMG_HEIGHT}",
          "@type": "ImageObject",
          "name": "Closeup view",
          "@context": "http://schema.org"
        },
        {
          "contentUrl": "https://jp.louisvuitton.com/images/is/image/lv/1/PP_VP_L/louis-vuitton-nbaジャージークラシックパンツ--HLP10WET2900_PM1_Side view.jpg?wid={IMG_WIDTH}&hei={IMG_HEIGHT}",
          "@type": "ImageObject",
          "name": "Side view",
          "@context": "http://schema.org"
        },
        {
          "contentUrl": "https://jp.louisvuitton.com/images/is/image/lv/1/PP_VP_L/louis-vuitton-nbaジャージークラシックパンツ--HLP10WET2900_PM1_Detail view.jpg?wid={IMG_WIDTH}&hei={IMG_HEIGHT}",
          "@type": "ImageObject",
          "name": "Detail view",
          "@context": "http://schema.org"
        }
      ],
      "url": "/jpn-jp/products/lvxnba-jersey-classic-pants-nvprod2800003v",
      "highEndTemplate": false,
      "sizeDisplayName": "40",
      "productId": "nvprod2800003v",
      "additionalProperty": [
        {
          "@type": "PropertyValue",
          "name": "colorIconURL",
          "value": "https://jp.louisvuitton.com/images/is/image/lv/1/LV/louis-vuitton--MKC-RTW-900_noir.jpg"
        },
        {
          "@type": "PropertyValue",
          "name": "detailedDescription",
          "value": "<ul><li>本体：ウール 59%、コットン 37%、ナイロン 4%</li><li>レギュラーフィット</li><li>モデル：胸囲 92cm、身長 185cm</li><li>モデル着用40サイズ</li><li>イタリア製</li><li>REF：HLP10WET2</li></ul>"
        },
        {
          "@type": "PropertyValue",
          "name": "activateEngraving",
          "value": false
        },
        {
          "@type": "PropertyValue",
          "name": "sellable",
          "value": true
        },
        {
          "@type": "PropertyValue",
          "name": "cscSellable",
          "value": true
        },
        {
          "@type": "PropertyValue",
          "name": "mom",
          "value": false
        },
        {
          "@type": "PropertyValue",
          "name": "locateInStore",
          "value": true
        },
        {
          "@type": "PropertyValue",
          "name": "materialGroupCode",
          "value": "Z05"
        },
        {
          "@type": "PropertyValue",
          "name": "filterCategories",
          "value": "Ready_To_Wear_Men"
        },
        {
          "@type": "PropertyValue",
          "name": "backOrderDisclaimer",
          "value": true
        },
        {
          "@type": "PropertyValue",
          "name": "backOrderFullDeposit",
          "value": false
        },
        {
          "@type": "PropertyValue",
          "name": "tryOnEnabled",
          "value": false
        },
        {
          "@type": "PropertyValue",
          "name": "isBundle",
          "value": false
        },
        {
          "@type": "PropertyValue",
          "name": "360ViewEnabled",
          "value": false
        }
      ],
      "category": [
        {
          "@type": "Thing",
          "url": "/jpn-jp/men/_/N-1cyoz77",
          "alternateName": "men",
          "name": "メンズ",
          "identifier": "homme"
        },
        {
          "@type": "Thing",
          "url": "/jpn-jp/men/ready-to-wear/_/N-1lpb5id",
          "alternateName": "ready-to-wear",
          "name": "プレタポルテ（洋服）",
          "identifier": "m-readytowear"
        },
        {
          "@type": "Thing",
          "url": "/jpn-jp/men/ready-to-wear/pants/_/N-13dbyz9",
          "alternateName": "pants",
          "name": "メンズ パンツ",
          "identifier": "m-pants-mrtw"
        }
      ],
      "disclaimers": {
        "value": "shipping_warning_bo",
        "popInContent": "global_backorder_info_popin_content",
        "popInTitle": "global_backorder_info_popin_title"
      },
      "color": "ノワール",
      "@context": "http://schema.org",
      "identifier": "1A8WXA"
    }
  ],
  "disambiguatingDescription": "今シーズンの「NBA」のテーマにフォーマルなひねりをプラスしたルック。ボクシーなシルエットに仕立てたジャケットにはNBAパッチをあしらい、内側にはバスケットボールから着想を得たNBA ストラテジック モノグラム･フラワー パターンを散りばめました。クラシカルなストレートカットのパンツと、コットンオックスフォードにフィルクーペの技法でマルチカラーのストラテジック モノグラム･フラワー パターンを遊び心いっぱいに描いたシャツを合わせています。",
  "_links": {
    "self": {
      "href": "/api/catalog/jpn-jp/product/nvprod2940006v"
    },
    "push": {
      "href": "/api/catalog/jpn-jp/product-push/nvprod2940006v"
    },
    "care-link": {
      "href": "/api/catalog/jpn-jp/care-link/nvprod2940006v"
    },
    "availability": {
      "href": "/api/catalog/jpn-jp/availability/nvprod2940006v"
    }
  },
  "@type": "Product",
  "sku": "nvsku2680006v",
  "isSimilarTo": [],
  "productTips": [],
  "url": "/jpn-jp/products/lvxnba-ii-look-06-nvprod2940006v",
  "accessoriesSKUs": [],
  "category": [
    {
      "@type": "Thing",
      "url": "/jpn-jp/men/_/N-1cyoz77",
      "alternateName": "men",
      "name": "メンズ",
      "identifier": "homme"
    },
    {
      "@type": "Thing",
      "url": "/jpn-jp/men/ready-to-wear/_/N-1lpb5id",
      "alternateName": "ready-to-wear",
      "name": "プレタポルテ（洋服）",
      "identifier": "m-readytowear"
    },
    {
      "@type": "Thing",
      "url": "/jpn-jp/men/ready-to-wear/view-by-look/_/N-1ui6ldg",
      "alternateName": "view-by-look",
      "name": "ルックブック",
      "identifier": "nvcat450010v"
    }
  ],
  "additionalProperty": [
    {
      "@type": "PropertyValue",
      "name": "hidePrice",
      "value": false
    },
    {
      "@type": "PropertyValue",
      "name": "subType",
      "value": "product"
    },
    {
      "@type": "PropertyValue",
      "name": "sizeGuide",
      "value": false
    }
  ],
  "name": "LVxNBA II - LOOK 06",
  "isRelatedTo": [],
  "@context": "http://schema.org",
  "identifier": "nvprod2940006v"
}
