{
  "model": [
    {
      "kitFlag": false,
      "_links": {
        "look": {
          "href": "/api/catalog/jpn-jp/skus/1AHCOA/look"
        },
        "parent": {
          "href": "/api/catalog/jpn-jp/product/nvprod6010130v"
        },
        "self": {
          "href": "/api/catalog/jpn-jp/product/1AHCOA"
        },
        "perso-details": {
          "href": "/api/catalog/jpn-jp/skus/1AHCOA/perso-detail"
        },
        "/api/rels/jpn-jp/add-to-cart-base/nvprod6010130v/1AHCOA/1": {
          "name": "add-to-cart",
          "href": "/api/cart/jpn-jp"
        }
      },
      "macroColor": "ブルー",
      "@type": "ProductModel",
      "identifierKey": "6d872d6d4b7e3d1334fdfb4e437551c2",
      "productDetailTabs": [],
      "kitExclusivity": false,
      "offers": {
        "priceSpecification": {
          "priceCurrency": "JPY",
          "price": 317900
        },
        "@type": "Offer",
        "price": "¥317,900"
      },
      "disambiguatingDescription": "｢Marque L. Vuitton Déposée｣シグネチャーを組み合わせた柔らかな質感の3D ダミエ･ジャカードがデザインを引き立てる、エフォートレスなデニムスケートパンツ。ウォッシュ加工が施されたインディゴデニムをイエローのトップステッチとエイジング加工を施したゴールドカラーのメタルパーツで彩り、ウエストにはヌバックのダミエ･ジャクロンパッチをあしらいました。ミックス & マッチが楽しめるパンツを同シリーズのジャケットと組み合わせれば、個性的なコーディネートに。<br><br>ご不明な点がございましたら、クライアントサービスまでお気軽にお問合せください。専任のクライアントアドバイザーが、素材やサイズなどの製品詳細、モデル着用イメージや関連アイテムのご案内など、お客様のご要望に合わせたスタイリング・アドバイスをご提供いたします。<br>また、サイズ違いなどによる返品・交換のご相談も承ります。詳細は<a href='https://jp.louisvuitton.com/jpn-jp/legal-privacy'><b>こちら。</b></a>",
      "image": [
        {
          "contentUrl": "https://jp.louisvuitton.com/images/is/image/lv/1/PP_VP_L/louis-vuitton-ダミエデニム-スケートパンツ-プレタポルテ-洋服--HSD48WGRT650_PM2_Front view.jpg?wid={IMG_WIDTH}&hei={IMG_HEIGHT}",
          "@type": "ImageObject",
          "name": "Front view",
          "@context": "http://schema.org"
        },
        {
          "contentUrl": "https://jp.louisvuitton.com/images/is/image/lv/1/PP_VP_L/louis-vuitton-ダミエデニム-スケートパンツ-プレタポルテ-洋服--HSD48WGRT650_PM1_Side view.jpg?wid={IMG_WIDTH}&hei={IMG_HEIGHT}",
          "@type": "ImageObject",
          "name": "Side view",
          "@context": "http://schema.org"
        },
        {
          "contentUrl": "https://jp.louisvuitton.com/images/is/image/lv/1/PP_VP_L/louis-vuitton-ダミエデニム-スケートパンツ-プレタポルテ-洋服--HSD48WGRT650_PM1_Back view.jpg?wid={IMG_WIDTH}&hei={IMG_HEIGHT}",
          "@type": "ImageObject",
          "name": "Back view",
          "@context": "http://schema.org"
        }
      ],
      "url": "/jpn-jp/products/damier-denim-skate-pants-nvprod6010130v",
      "sizeDisplayName": "27",
      "category": [
        {
          "@type": "Thing",
          "url": "/jpn-jp/men/_/N-t18ui4cq",
          "alternateName": "men",
          "name": "メンズ",
          "identifier": "homme"
        },
        {
          "@type": "Thing",
          "url": "/jpn-jp/men/ready-to-wear/_/N-t1b9f3zb",
          "alternateName": "ready-to-wear",
          "name": "プレタポルテ(洋服)",
          "identifier": "m-readytowear"
        },
        {
          "@type": "Thing",
          "url": "/jpn-jp/men/ready-to-wear/denim/_/N-tgmiooy",
          "alternateName": "denim",
          "name": "メンズ デニム",
          "identifier": "m-denim-mrtw"
        }
      ],
      "additionalProperty": [
        {
          "@type": "PropertyValue",
          "name": "colorIconURL",
          "value": "https://jp.louisvuitton.com/images/is/image/lv/1/LV/louis-vuitton--MKC-RTW-650_indigo.jpg"
        },
        {
          "@type": "PropertyValue",
          "name": "detailedDescription",
          "value": "<ul><li>レギュラーフィット</li><li>カラー：インディゴ</li><li>本体：コットン 91%、ポリエステル 8%、ポリウレタン 1%</li><li>ジャカード織りのシグネチャー</li><li>ヴィンテージ風ゴールドカラーのドーム型ボタン</li><li>ヴィンテージ風ゴールドカラーのリベット</li><li>クラシックな5ポケットデニム</li><li>ヌバックのシグネチャーのジャクロンパッチ</li><li>イタリア製</li></ul>"
        },
        {
          "@type": "PropertyValue",
          "name": "englishProductName",
          "value": "Damier Denim Skate Pants   "
        },
        {
          "@type": "PropertyValue",
          "name": "activateEngraving",
          "value": false
        },
        {
          "@type": "PropertyValue",
          "name": "sellable",
          "value": true
        },
        {
          "@type": "PropertyValue",
          "name": "cscSellable",
          "value": true
        },
        {
          "@type": "PropertyValue",
          "name": "mom",
          "value": false
        },
        {
          "@type": "PropertyValue",
          "name": "locateInStore",
          "value": true
        },
        {
          "@type": "PropertyValue",
          "name": "materialGroupCode",
          "value": "Z05"
        },
        {
          "@type": "PropertyValue",
          "name": "filterCategories",
          "value": "Ready_To_Wear_Men"
        },
        {
          "@type": "PropertyValue",
          "name": "backOrderDisclaimer",
          "value": true
        },
        {
          "@type": "PropertyValue",
          "name": "backOrderFullDeposit",
          "value": false
        },
        {
          "@type": "PropertyValue",
          "name": "diamondEngravingEnabled",
          "value": false
        },
        {
          "@type": "PropertyValue",
          "name": "tryOnEnabled",
          "value": false
        },
        {
          "@type": "PropertyValue",
          "name": "video360Enabled",
          "value": false
        },
        {
          "@type": "PropertyValue",
          "name": "isBundle",
          "value": false
        },
        {
          "@type": "PropertyValue",
          "name": "eligibleToAgec",
          "value": true
        },
        {
          "@type": "PropertyValue",
          "name": "hasLanguagePanel",
          "value": false
        },
        {
          "@type": "PropertyValue",
          "name": "bannerList",
          "value": [
            {
              "commercialBanner": "top_banner_content_category_1"
            },
            {
              "commercialBanner": "top_banner_content_category_2"
            },
            {
              "commercialBanner": "top_banner_content_category_3"
            },
            {
              "commercialBanner": "top_banner_content_category_4"
            }
          ]
        }
      ],
      "careLink": {
        "sections": []
      },
      "collectibles": false,
      "identifier": "1AHCOA",
      "defaultFamilySapDisplayName": "PANTS DENIM M",
      "productVisible": true,
      "name": "ダミエデニム スケートパンツ",
      "packagingVariation": "",
      "highEndTemplate": false,
      "productId": "nvprod6010130v",
      "hasLanguagePanel": false,
      "disclaimers": {
        "customDisclaimer": false,
        "value": "dynamic_shipping_warning_bo",
        "popInContent": "dynamic_global_backorder_info_popin_content",
        "popInTitle": "dynamic_global_backorder_info_popin_title"
      },
      "color": "Indigo",
      "@context": "http://schema.org"
    },
    {
      "kitFlag": false,
      "_links": {
        "look": {
          "href": "/api/catalog/jpn-jp/skus/1AHCOB/look"
        },
        "parent": {
          "href": "/api/catalog/jpn-jp/product/nvprod6010130v"
        },
        "self": {
          "href": "/api/catalog/jpn-jp/product/1AHCOB"
        },
        "perso-details": {
          "href": "/api/catalog/jpn-jp/skus/1AHCOB/perso-detail"
        },
        "/api/rels/jpn-jp/add-to-cart-base/nvprod6010130v/1AHCOB/1": {
          "name": "add-to-cart",
          "href": "/api/cart/jpn-jp"
        }
      },
      "macroColor": "ブルー",
      "@type": "ProductModel",
      "identifierKey": "84cb39b709c27090360b995179566d4d",
      "productDetailTabs": [],
      "kitExclusivity": false,
      "offers": {
        "priceSpecification": {
          "priceCurrency": "JPY",
          "price": 317900
        },
        "@type": "Offer",
        "price": "¥317,900"
      },
      "disambiguatingDescription": "｢Marque L. Vuitton Déposée｣シグネチャーを組み合わせた柔らかな質感の3D ダミエ･ジャカードがデザインを引き立てる、エフォートレスなデニムスケートパンツ。ウォッシュ加工が施されたインディゴデニムをイエローのトップステッチとエイジング加工を施したゴールドカラーのメタルパーツで彩り、ウエストにはヌバックのダミエ･ジャクロンパッチをあしらいました。ミックス & マッチが楽しめるパンツを同シリーズのジャケットと組み合わせれば、個性的なコーディネートに。<br><br>ご不明な点がございましたら、クライアントサービスまでお気軽にお問合せください。専任のクライアントアドバイザーが、素材やサイズなどの製品詳細、モデル着用イメージや関連アイテムのご案内など、お客様のご要望に合わせたスタイリング・アドバイスをご提供いたします。<br>また、サイズ違いなどによる返品・交換のご相談も承ります。詳細は<a href='https://jp.louisvuitton.com/jpn-jp/legal-privacy'><b>こちら。</b></a>",
      "image": [
        {
          "contentUrl": "https://jp.louisvuitton.com/images/is/image/lv/1/PP_VP_L/louis-vuitton-ダミエデニム-スケートパンツ-プレタポルテ-洋服--HSD48WGRT650_PM2_Front view.jpg?wid={IMG_WIDTH}&hei={IMG_HEIGHT}",
          "@type": "ImageObject",
          "name": "Front view",
          "@context": "http://schema.org"
        },
        {
          "contentUrl": "https://jp.louisvuitton.com/images/is/image/lv/1/PP_VP_L/louis-vuitton-ダミエデニム-スケートパンツ-プレタポルテ-洋服--HSD48WGRT650_PM1_Side view.jpg?wid={IMG_WIDTH}&hei={IMG_HEIGHT}",
          "@type": "ImageObject",
          "name": "Side view",
          "@context": "http://schema.org"
        },
        {
          "contentUrl": "https://jp.louisvuitton.com/images/is/image/lv/1/PP_VP_L/louis-vuitton-ダミエデニム-スケートパンツ-プレタポルテ-洋服--HSD48WGRT650_PM1_Back view.jpg?wid={IMG_WIDTH}&hei={IMG_HEIGHT}",
          "@type": "ImageObject",
          "name": "Back view",
          "@context": "http://schema.org"
        }
      ],
      "url": "/jpn-jp/products/damier-denim-skate-pants-nvprod6010130v",
      "sizeDisplayName": "28",
      "category": [
        {
          "@type": "Thing",
          "url": "/jpn-jp/men/_/N-t18ui4cq",
          "alternateName": "men",
          "name": "メンズ",
          "identifier": "homme"
        },
        {
          "@type": "Thing",
          "url": "/jpn-jp/men/ready-to-wear/_/N-t1b9f3zb",
          "alternateName": "ready-to-wear",
          "name": "プレタポルテ(洋服)",
          "identifier": "m-readytowear"
        },
        {
          "@type": "Thing",
          "url": "/jpn-jp/men/ready-to-wear/denim/_/N-tgmiooy",
          "alternateName": "denim",
          "name": "メンズ デニム",
          "identifier": "m-denim-mrtw"
        }
      ],
      "additionalProperty": [
        {
          "@type": "PropertyValue",
          "name": "colorIconURL",
          "value": "https://jp.louisvuitton.com/images/is/image/lv/1/LV/louis-vuitton--MKC-RTW-650_indigo.jpg"
        },
        {
          "@type": "PropertyValue",
          "name": "detailedDescription",
          "value": "<ul><li>レギュラーフィット</li><li>カラー：インディゴ</li><li>本体：コットン 91%、ポリエステル 8%、ポリウレタン 1%</li><li>ジャカード織りのシグネチャー</li><li>ヴィンテージ風ゴールドカラーのドーム型ボタン</li><li>ヴィンテージ風ゴールドカラーのリベット</li><li>クラシックな5ポケットデニム</li><li>ヌバックのシグネチャーのジャクロンパッチ</li><li>イタリア製</li></ul>"
        },
        {
          "@type": "PropertyValue",
          "name": "englishProductName",
          "value": "Damier Denim Skate Pants   "
        },
        {
          "@type": "PropertyValue",
          "name": "activateEngraving",
          "value": false
        },
        {
          "@type": "PropertyValue",
          "name": "sellable",
          "value": true
        },
        {
          "@type": "PropertyValue",
          "name": "cscSellable",
          "value": true
        },
        {
          "@type": "PropertyValue",
          "name": "mom",
          "value": false
        },
        {
          "@type": "PropertyValue",
          "name": "locateInStore",
          "value": true
        },
        {
          "@type": "PropertyValue",
          "name": "materialGroupCode",
          "value": "Z05"
        },
        {
          "@type": "PropertyValue",
          "name": "filterCategories",
          "value": "Ready_To_Wear_Men"
        },
        {
          "@type": "PropertyValue",
          "name": "backOrderDisclaimer",
          "value": true
        },
        {
          "@type": "PropertyValue",
          "name": "backOrderFullDeposit",
          "value": false
        },
        {
          "@type": "PropertyValue",
          "name": "diamondEngravingEnabled",
          "value": false
        },
        {
          "@type": "PropertyValue",
          "name": "tryOnEnabled",
          "value": false
        },
        {
          "@type": "PropertyValue",
          "name": "video360Enabled",
          "value": false
        },
        {
          "@type": "PropertyValue",
          "name": "isBundle",
          "value": false
        },
        {
          "@type": "PropertyValue",
          "name": "eligibleToAgec",
          "value": true
        },
        {
          "@type": "PropertyValue",
          "name": "hasLanguagePanel",
          "value": false
        },
        {
          "@type": "PropertyValue",
          "name": "bannerList",
          "value": [
            {
              "commercialBanner": "top_banner_content_category_1"
            },
            {
              "commercialBanner": "top_banner_content_category_2"
            },
            {
              "commercialBanner": "top_banner_content_category_3"
            },
            {
              "commercialBanner": "top_banner_content_category_4"
            }
          ]
        }
      ],
      "careLink": {
        "sections": []
      },
      "collectibles": false,
      "identifier": "1AHCOB",
      "defaultFamilySapDisplayName": "PANTS DENIM M",
      "productVisible": true,
      "name": "ダミエデニム スケートパンツ",
      "packagingVariation": "",
      "highEndTemplate": false,
      "productId": "nvprod6010130v",
      "hasLanguagePanel": false,
      "disclaimers": {
        "customDisclaimer": false,
        "value": "dynamic_shipping_warning_bo",
        "popInContent": "dynamic_global_backorder_info_popin_content",
        "popInTitle": "dynamic_global_backorder_info_popin_title"
      },
      "color": "Indigo",
      "@context": "http://schema.org"
    },
    {
      "kitFlag": false,
      "_links": {
        "look": {
          "href": "/api/catalog/jpn-jp/skus/1AHCOC/look"
        },
        "parent": {
          "href": "/api/catalog/jpn-jp/product/nvprod6010130v"
        },
        "self": {
          "href": "/api/catalog/jpn-jp/product/1AHCOC"
        },
        "perso-details": {
          "href": "/api/catalog/jpn-jp/skus/1AHCOC/perso-detail"
        },
        "/api/rels/jpn-jp/add-to-cart-base/nvprod6010130v/1AHCOC/1": {
          "name": "add-to-cart",
          "href": "/api/cart/jpn-jp"
        }
      },
      "macroColor": "ブルー",
      "@type": "ProductModel",
      "identifierKey": "f9da4e7054371b449f571f3ba632f5bf",
      "productDetailTabs": [],
      "kitExclusivity": false,
      "offers": {
        "priceSpecification": {
          "priceCurrency": "JPY",
          "price": 317900
        },
        "@type": "Offer",
        "price": "¥317,900"
      },
      "disambiguatingDescription": "｢Marque L. Vuitton Déposée｣シグネチャーを組み合わせた柔らかな質感の3D ダミエ･ジャカードがデザインを引き立てる、エフォートレスなデニムスケートパンツ。ウォッシュ加工が施されたインディゴデニムをイエローのトップステッチとエイジング加工を施したゴールドカラーのメタルパーツで彩り、ウエストにはヌバックのダミエ･ジャクロンパッチをあしらいました。ミックス & マッチが楽しめるパンツを同シリーズのジャケットと組み合わせれば、個性的なコーディネートに。<br><br>ご不明な点がございましたら、クライアントサービスまでお気軽にお問合せください。専任のクライアントアドバイザーが、素材やサイズなどの製品詳細、モデル着用イメージや関連アイテムのご案内など、お客様のご要望に合わせたスタイリング・アドバイスをご提供いたします。<br>また、サイズ違いなどによる返品・交換のご相談も承ります。詳細は<a href='https://jp.louisvuitton.com/jpn-jp/legal-privacy'><b>こちら。</b></a>",
      "image": [
        {
          "contentUrl": "https://jp.louisvuitton.com/images/is/image/lv/1/PP_VP_L/louis-vuitton-ダミエデニム-スケートパンツ-プレタポルテ-洋服--HSD48WGRT650_PM2_Front view.jpg?wid={IMG_WIDTH}&hei={IMG_HEIGHT}",
          "@type": "ImageObject",
          "name": "Front view",
          "@context": "http://schema.org"
        },
        {
          "contentUrl": "https://jp.louisvuitton.com/images/is/image/lv/1/PP_VP_L/louis-vuitton-ダミエデニム-スケートパンツ-プレタポルテ-洋服--HSD48WGRT650_PM1_Side view.jpg?wid={IMG_WIDTH}&hei={IMG_HEIGHT}",
          "@type": "ImageObject",
          "name": "Side view",
          "@context": "http://schema.org"
        },
        {
          "contentUrl": "https://jp.louisvuitton.com/images/is/image/lv/1/PP_VP_L/louis-vuitton-ダミエデニム-スケートパンツ-プレタポルテ-洋服--HSD48WGRT650_PM1_Back view.jpg?wid={IMG_WIDTH}&hei={IMG_HEIGHT}",
          "@type": "ImageObject",
          "name": "Back view",
          "@context": "http://schema.org"
        }
      ],
      "url": "/jpn-jp/products/damier-denim-skate-pants-nvprod6010130v",
      "sizeDisplayName": "29",
      "category": [
        {
          "@type": "Thing",
          "url": "/jpn-jp/men/_/N-t18ui4cq",
          "alternateName": "men",
          "name": "メンズ",
          "identifier": "homme"
        },
        {
          "@type": "Thing",
          "url": "/jpn-jp/men/ready-to-wear/_/N-t1b9f3zb",
          "alternateName": "ready-to-wear",
          "name": "プレタポルテ(洋服)",
          "identifier": "m-readytowear"
        },
        {
          "@type": "Thing",
          "url": "/jpn-jp/men/ready-to-wear/denim/_/N-tgmiooy",
          "alternateName": "denim",
          "name": "メンズ デニム",
          "identifier": "m-denim-mrtw"
        }
      ],
      "additionalProperty": [
        {
          "@type": "PropertyValue",
          "name": "colorIconURL",
          "value": "https://jp.louisvuitton.com/images/is/image/lv/1/LV/louis-vuitton--MKC-RTW-650_indigo.jpg"
        },
        {
          "@type": "PropertyValue",
          "name": "detailedDescription",
          "value": "<ul><li>レギュラーフィット</li><li>カラー：インディゴ</li><li>本体：コットン 91%、ポリエステル 8%、ポリウレタン 1%</li><li>ジャカード織りのシグネチャー</li><li>ヴィンテージ風ゴールドカラーのドーム型ボタン</li><li>ヴィンテージ風ゴールドカラーのリベット</li><li>クラシックな5ポケットデニム</li><li>ヌバックのシグネチャーのジャクロンパッチ</li><li>イタリア製</li></ul>"
        },
        {
          "@type": "PropertyValue",
          "name": "englishProductName",
          "value": "Damier Denim Skate Pants   "
        },
        {
          "@type": "PropertyValue",
          "name": "activateEngraving",
          "value": false
        },
        {
          "@type": "PropertyValue",
          "name": "sellable",
          "value": true
        },
        {
          "@type": "PropertyValue",
          "name": "cscSellable",
          "value": true
        },
        {
          "@type": "PropertyValue",
          "name": "mom",
          "value": false
        },
        {
          "@type": "PropertyValue",
          "name": "locateInStore",
          "value": true
        },
        {
          "@type": "PropertyValue",
          "name": "materialGroupCode",
          "value": "Z05"
        },
        {
          "@type": "PropertyValue",
          "name": "filterCategories",
          "value": "Ready_To_Wear_Men"
        },
        {
          "@type": "PropertyValue",
          "name": "backOrderDisclaimer",
          "value": true
        },
        {
          "@type": "PropertyValue",
          "name": "backOrderFullDeposit",
          "value": false
        },
        {
          "@type": "PropertyValue",
          "name": "diamondEngravingEnabled",
          "value": false
        },
        {
          "@type": "PropertyValue",
          "name": "tryOnEnabled",
          "value": false
        },
        {
          "@type": "PropertyValue",
          "name": "video360Enabled",
          "value": false
        },
        {
          "@type": "PropertyValue",
          "name": "isBundle",
          "value": false
        },
        {
          "@type": "PropertyValue",
          "name": "eligibleToAgec",
          "value": true
        },
        {
          "@type": "PropertyValue",
          "name": "hasLanguagePanel",
          "value": false
        },
        {
          "@type": "PropertyValue",
          "name": "bannerList",
          "value": [
            {
              "commercialBanner": "top_banner_content_category_1"
            },
            {
              "commercialBanner": "top_banner_content_category_2"
            },
            {
              "commercialBanner": "top_banner_content_category_3"
            },
            {
              "commercialBanner": "top_banner_content_category_4"
            }
          ]
        }
      ],
      "careLink": {
        "sections": []
      },
      "collectibles": false,
      "identifier": "1AHCOC",
      "defaultFamilySapDisplayName": "PANTS DENIM M",
      "productVisible": true,
      "name": "ダミエデニム スケートパンツ",
      "packagingVariation": "",
      "highEndTemplate": false,
      "productId": "nvprod6010130v",
      "hasLanguagePanel": false,
      "disclaimers": {
        "customDisclaimer": false,
        "value": "dynamic_shipping_warning_bo",
        "popInContent": "dynamic_global_backorder_info_popin_content",
        "popInTitle": "dynamic_global_backorder_info_popin_title"
      },
      "color": "Indigo",
      "@context": "http://schema.org"
    },
    {
      "kitFlag": false,
      "_links": {
        "look": {
          "href": "/api/catalog/jpn-jp/skus/1AHCOD/look"
        },
        "parent": {
          "href": "/api/catalog/jpn-jp/product/nvprod6010130v"
        },
        "self": {
          "href": "/api/catalog/jpn-jp/product/1AHCOD"
        },
        "perso-details": {
          "href": "/api/catalog/jpn-jp/skus/1AHCOD/perso-detail"
        },
        "/api/rels/jpn-jp/add-to-cart-base/nvprod6010130v/1AHCOD/1": {
          "name": "add-to-cart",
          "href": "/api/cart/jpn-jp"
        }
      },
      "macroColor": "ブルー",
      "@type": "ProductModel",
      "identifierKey": "ae6e135a92ae6cdbc985577b6e185417",
      "productDetailTabs": [],
      "kitExclusivity": false,
      "offers": {
        "priceSpecification": {
          "priceCurrency": "JPY",
          "price": 317900
        },
        "@type": "Offer",
        "price": "¥317,900"
      },
      "disambiguatingDescription": "｢Marque L. Vuitton Déposée｣シグネチャーを組み合わせた柔らかな質感の3D ダミエ･ジャカードがデザインを引き立てる、エフォートレスなデニムスケートパンツ。ウォッシュ加工が施されたインディゴデニムをイエローのトップステッチとエイジング加工を施したゴールドカラーのメタルパーツで彩り、ウエストにはヌバックのダミエ･ジャクロンパッチをあしらいました。ミックス & マッチが楽しめるパンツを同シリーズのジャケットと組み合わせれば、個性的なコーディネートに。<br><br>ご不明な点がございましたら、クライアントサービスまでお気軽にお問合せください。専任のクライアントアドバイザーが、素材やサイズなどの製品詳細、モデル着用イメージや関連アイテムのご案内など、お客様のご要望に合わせたスタイリング・アドバイスをご提供いたします。<br>また、サイズ違いなどによる返品・交換のご相談も承ります。詳細は<a href='https://jp.louisvuitton.com/jpn-jp/legal-privacy'><b>こちら。</b></a>",
      "image": [
        {
          "contentUrl": "https://jp.louisvuitton.com/images/is/image/lv/1/PP_VP_L/louis-vuitton-ダミエデニム-スケートパンツ-プレタポルテ-洋服--HSD48WGRT650_PM2_Front view.jpg?wid={IMG_WIDTH}&hei={IMG_HEIGHT}",
          "@type": "ImageObject",
          "name": "Front view",
          "@context": "http://schema.org"
        },
        {
          "contentUrl": "https://jp.louisvuitton.com/images/is/image/lv/1/PP_VP_L/louis-vuitton-ダミエデニム-スケートパンツ-プレタポルテ-洋服--HSD48WGRT650_PM1_Side view.jpg?wid={IMG_WIDTH}&hei={IMG_HEIGHT}",
          "@type": "ImageObject",
          "name": "Side view",
          "@context": "http://schema.org"
        },
        {
          "contentUrl": "https://jp.louisvuitton.com/images/is/image/lv/1/PP_VP_L/louis-vuitton-ダミエデニム-スケートパンツ-プレタポルテ-洋服--HSD48WGRT650_PM1_Back view.jpg?wid={IMG_WIDTH}&hei={IMG_HEIGHT}",
          "@type": "ImageObject",
          "name": "Back view",
          "@context": "http://schema.org"
        }
      ],
      "url": "/jpn-jp/products/damier-denim-skate-pants-nvprod6010130v",
      "sizeDisplayName": "30",
      "category": [
        {
          "@type": "Thing",
          "url": "/jpn-jp/men/_/N-t18ui4cq",
          "alternateName": "men",
          "name": "メンズ",
          "identifier": "homme"
        },
        {
          "@type": "Thing",
          "url": "/jpn-jp/men/ready-to-wear/_/N-t1b9f3zb",
          "alternateName": "ready-to-wear",
          "name": "プレタポルテ(洋服)",
          "identifier": "m-readytowear"
        },
        {
          "@type": "Thing",
          "url": "/jpn-jp/men/ready-to-wear/denim/_/N-tgmiooy",
          "alternateName": "denim",
          "name": "メンズ デニム",
          "identifier": "m-denim-mrtw"
        }
      ],
      "additionalProperty": [
        {
          "@type": "PropertyValue",
          "name": "colorIconURL",
          "value": "https://jp.louisvuitton.com/images/is/image/lv/1/LV/louis-vuitton--MKC-RTW-650_indigo.jpg"
        },
        {
          "@type": "PropertyValue",
          "name": "detailedDescription",
          "value": "<ul><li>レギュラーフィット</li><li>カラー：インディゴ</li><li>本体：コットン 91%、ポリエステル 8%、ポリウレタン 1%</li><li>ジャカード織りのシグネチャー</li><li>ヴィンテージ風ゴールドカラーのドーム型ボタン</li><li>ヴィンテージ風ゴールドカラーのリベット</li><li>クラシックな5ポケットデニム</li><li>ヌバックのシグネチャーのジャクロンパッチ</li><li>イタリア製</li></ul>"
        },
        {
          "@type": "PropertyValue",
          "name": "englishProductName",
          "value": "Damier Denim Skate Pants   "
        },
        {
          "@type": "PropertyValue",
          "name": "activateEngraving",
          "value": false
        },
        {
          "@type": "PropertyValue",
          "name": "sellable",
          "value": true
        },
        {
          "@type": "PropertyValue",
          "name": "cscSellable",
          "value": true
        },
        {
          "@type": "PropertyValue",
          "name": "mom",
          "value": false
        },
        {
          "@type": "PropertyValue",
          "name": "locateInStore",
          "value": true
        },
        {
          "@type": "PropertyValue",
          "name": "materialGroupCode",
          "value": "Z05"
        },
        {
          "@type": "PropertyValue",
          "name": "filterCategories",
          "value": "Ready_To_Wear_Men"
        },
        {
          "@type": "PropertyValue",
          "name": "backOrderDisclaimer",
          "value": true
        },
        {
          "@type": "PropertyValue",
          "name": "backOrderFullDeposit",
          "value": false
        },
        {
          "@type": "PropertyValue",
          "name": "diamondEngravingEnabled",
          "value": false
        },
        {
          "@type": "PropertyValue",
          "name": "tryOnEnabled",
          "value": false
        },
        {
          "@type": "PropertyValue",
          "name": "video360Enabled",
          "value": false
        },
        {
          "@type": "PropertyValue",
          "name": "isBundle",
          "value": false
        },
        {
          "@type": "PropertyValue",
          "name": "eligibleToAgec",
          "value": true
        },
        {
          "@type": "PropertyValue",
          "name": "hasLanguagePanel",
          "value": false
        },
        {
          "@type": "PropertyValue",
          "name": "bannerList",
          "value": [
            {
              "commercialBanner": "top_banner_content_category_1"
            },
            {
              "commercialBanner": "top_banner_content_category_2"
            },
            {
              "commercialBanner": "top_banner_content_category_3"
            },
            {
              "commercialBanner": "top_banner_content_category_4"
            }
          ]
        }
      ],
      "careLink": {
        "sections": []
      },
      "collectibles": false,
      "identifier": "1AHCOD",
      "defaultFamilySapDisplayName": "PANTS DENIM M",
      "productVisible": true,
      "name": "ダミエデニム スケートパンツ",
      "packagingVariation": "",
      "highEndTemplate": false,
      "productId": "nvprod6010130v",
      "hasLanguagePanel": false,
      "disclaimers": {
        "customDisclaimer": false,
        "value": "dynamic_shipping_warning_bo",
        "popInContent": "dynamic_global_backorder_info_popin_content",
        "popInTitle": "dynamic_global_backorder_info_popin_title"
      },
      "color": "Indigo",
      "@context": "http://schema.org"
    },
    {
      "kitFlag": false,
      "_links": {
        "look": {
          "href": "/api/catalog/jpn-jp/skus/1AHCOE/look"
        },
        "parent": {
          "href": "/api/catalog/jpn-jp/product/nvprod6010130v"
        },
        "self": {
          "href": "/api/catalog/jpn-jp/product/1AHCOE"
        },
        "perso-details": {
          "href": "/api/catalog/jpn-jp/skus/1AHCOE/perso-detail"
        },
        "/api/rels/jpn-jp/add-to-cart-base/nvprod6010130v/1AHCOE/1": {
          "name": "add-to-cart",
          "href": "/api/cart/jpn-jp"
        }
      },
      "macroColor": "ブルー",
      "@type": "ProductModel",
      "identifierKey": "a7ffb79ab4f88dea027d6bc51c48a913",
      "productDetailTabs": [],
      "kitExclusivity": false,
      "offers": {
        "priceSpecification": {
          "priceCurrency": "JPY",
          "price": 317900
        },
        "@type": "Offer",
        "price": "¥317,900"
      },
      "disambiguatingDescription": "｢Marque L. Vuitton Déposée｣シグネチャーを組み合わせた柔らかな質感の3D ダミエ･ジャカードがデザインを引き立てる、エフォートレスなデニムスケートパンツ。ウォッシュ加工が施されたインディゴデニムをイエローのトップステッチとエイジング加工を施したゴールドカラーのメタルパーツで彩り、ウエストにはヌバックのダミエ･ジャクロンパッチをあしらいました。ミックス & マッチが楽しめるパンツを同シリーズのジャケットと組み合わせれば、個性的なコーディネートに。<br><br>ご不明な点がございましたら、クライアントサービスまでお気軽にお問合せください。専任のクライアントアドバイザーが、素材やサイズなどの製品詳細、モデル着用イメージや関連アイテムのご案内など、お客様のご要望に合わせたスタイリング・アドバイスをご提供いたします。<br>また、サイズ違いなどによる返品・交換のご相談も承ります。詳細は<a href='https://jp.louisvuitton.com/jpn-jp/legal-privacy'><b>こちら。</b></a>",
      "image": [
        {
          "contentUrl": "https://jp.louisvuitton.com/images/is/image/lv/1/PP_VP_L/louis-vuitton-ダミエデニム-スケートパンツ-プレタポルテ-洋服--HSD48WGRT650_PM2_Front view.jpg?wid={IMG_WIDTH}&hei={IMG_HEIGHT}",
          "@type": "ImageObject",
          "name": "Front view",
          "@context": "http://schema.org"
        },
        {
          "contentUrl": "https://jp.louisvuitton.com/images/is/image/lv/1/PP_VP_L/louis-vuitton-ダミエデニム-スケートパンツ-プレタポルテ-洋服--HSD48WGRT650_PM1_Side view.jpg?wid={IMG_WIDTH}&hei={IMG_HEIGHT}",
          "@type": "ImageObject",
          "name": "Side view",
          "@context": "http://schema.org"
        },
        {
          "contentUrl": "https://jp.louisvuitton.com/images/is/image/lv/1/PP_VP_L/louis-vuitton-ダミエデニム-スケートパンツ-プレタポルテ-洋服--HSD48WGRT650_PM1_Back view.jpg?wid={IMG_WIDTH}&hei={IMG_HEIGHT}",
          "@type": "ImageObject",
          "name": "Back view",
          "@context": "http://schema.org"
        }
      ],
      "url": "/jpn-jp/products/damier-denim-skate-pants-nvprod6010130v",
      "sizeDisplayName": "31",
      "category": [
        {
          "@type": "Thing",
          "url": "/jpn-jp/men/_/N-t18ui4cq",
          "alternateName": "men",
          "name": "メンズ",
          "identifier": "homme"
        },
        {
          "@type": "Thing",
          "url": "/jpn-jp/men/ready-to-wear/_/N-t1b9f3zb",
          "alternateName": "ready-to-wear",
          "name": "プレタポルテ(洋服)",
          "identifier": "m-readytowear"
        },
        {
          "@type": "Thing",
          "url": "/jpn-jp/men/ready-to-wear/denim/_/N-tgmiooy",
          "alternateName": "denim",
          "name": "メンズ デニム",
          "identifier": "m-denim-mrtw"
        }
      ],
      "additionalProperty": [
        {
          "@type": "PropertyValue",
          "name": "colorIconURL",
          "value": "https://jp.louisvuitton.com/images/is/image/lv/1/LV/louis-vuitton--MKC-RTW-650_indigo.jpg"
        },
        {
          "@type": "PropertyValue",
          "name": "detailedDescription",
          "value": "<ul><li>レギュラーフィット</li><li>カラー：インディゴ</li><li>本体：コットン 91%、ポリエステル 8%、ポリウレタン 1%</li><li>ジャカード織りのシグネチャー</li><li>ヴィンテージ風ゴールドカラーのドーム型ボタン</li><li>ヴィンテージ風ゴールドカラーのリベット</li><li>クラシックな5ポケットデニム</li><li>ヌバックのシグネチャーのジャクロンパッチ</li><li>イタリア製</li></ul>"
        },
        {
          "@type": "PropertyValue",
          "name": "englishProductName",
          "value": "Damier Denim Skate Pants   "
        },
        {
          "@type": "PropertyValue",
          "name": "activateEngraving",
          "value": false
        },
        {
          "@type": "PropertyValue",
          "name": "sellable",
          "value": true
        },
        {
          "@type": "PropertyValue",
          "name": "cscSellable",
          "value": true
        },
        {
          "@type": "PropertyValue",
          "name": "mom",
          "value": false
        },
        {
          "@type": "PropertyValue",
          "name": "locateInStore",
          "value": true
        },
        {
          "@type": "PropertyValue",
          "name": "materialGroupCode",
          "value": "Z05"
        },
        {
          "@type": "PropertyValue",
          "name": "filterCategories",
          "value": "Ready_To_Wear_Men"
        },
        {
          "@type": "PropertyValue",
          "name": "backOrderDisclaimer",
          "value": true
        },
        {
          "@type": "PropertyValue",
          "name": "backOrderFullDeposit",
          "value": false
        },
        {
          "@type": "PropertyValue",
          "name": "diamondEngravingEnabled",
          "value": false
        },
        {
          "@type": "PropertyValue",
          "name": "tryOnEnabled",
          "value": false
        },
        {
          "@type": "PropertyValue",
          "name": "video360Enabled",
          "value": false
        },
        {
          "@type": "PropertyValue",
          "name": "isBundle",
          "value": false
        },
        {
          "@type": "PropertyValue",
          "name": "eligibleToAgec",
          "value": true
        },
        {
          "@type": "PropertyValue",
          "name": "hasLanguagePanel",
          "value": false
        },
        {
          "@type": "PropertyValue",
          "name": "bannerList",
          "value": [
            {
              "commercialBanner": "top_banner_content_category_1"
            },
            {
              "commercialBanner": "top_banner_content_category_2"
            },
            {
              "commercialBanner": "top_banner_content_category_3"
            },
            {
              "commercialBanner": "top_banner_content_category_4"
            }
          ]
        }
      ],
      "careLink": {
        "sections": []
      },
      "collectibles": false,
      "identifier": "1AHCOE",
      "defaultFamilySapDisplayName": "PANTS DENIM M",
      "productVisible": true,
      "name": "ダミエデニム スケートパンツ",
      "packagingVariation": "",
      "highEndTemplate": false,
      "productId": "nvprod6010130v",
      "hasLanguagePanel": false,
      "disclaimers": {
        "customDisclaimer": false,
        "value": "dynamic_shipping_warning_bo",
        "popInContent": "dynamic_global_backorder_info_popin_content",
        "popInTitle": "dynamic_global_backorder_info_popin_title"
      },
      "color": "Indigo",
      "@context": "http://schema.org"
    },
    {
      "kitFlag": false,
      "_links": {
        "look": {
          "href": "/api/catalog/jpn-jp/skus/1AHCOF/look"
        },
        "parent": {
          "href": "/api/catalog/jpn-jp/product/nvprod6010130v"
        },
        "self": {
          "href": "/api/catalog/jpn-jp/product/1AHCOF"
        },
        "perso-details": {
          "href": "/api/catalog/jpn-jp/skus/1AHCOF/perso-detail"
        },
        "/api/rels/jpn-jp/add-to-cart-base/nvprod6010130v/1AHCOF/1": {
          "name": "add-to-cart",
          "href": "/api/cart/jpn-jp"
        }
      },
      "macroColor": "ブルー",
      "@type": "ProductModel",
      "identifierKey": "0c03c30b415bf5f976ac3940e635b720",
      "productDetailTabs": [],
      "kitExclusivity": false,
      "offers": {
        "priceSpecification": {
          "priceCurrency": "JPY",
          "price": 317900
        },
        "@type": "Offer",
        "price": "¥317,900"
      },
      "disambiguatingDescription": "｢Marque L. Vuitton Déposée｣シグネチャーを組み合わせた柔らかな質感の3D ダミエ･ジャカードがデザインを引き立てる、エフォートレスなデニムスケートパンツ。ウォッシュ加工が施されたインディゴデニムをイエローのトップステッチとエイジング加工を施したゴールドカラーのメタルパーツで彩り、ウエストにはヌバックのダミエ･ジャクロンパッチをあしらいました。ミックス & マッチが楽しめるパンツを同シリーズのジャケットと組み合わせれば、個性的なコーディネートに。<br><br>ご不明な点がございましたら、クライアントサービスまでお気軽にお問合せください。専任のクライアントアドバイザーが、素材やサイズなどの製品詳細、モデル着用イメージや関連アイテムのご案内など、お客様のご要望に合わせたスタイリング・アドバイスをご提供いたします。<br>また、サイズ違いなどによる返品・交換のご相談も承ります。詳細は<a href='https://jp.louisvuitton.com/jpn-jp/legal-privacy'><b>こちら。</b></a>",
      "image": [
        {
          "contentUrl": "https://jp.louisvuitton.com/images/is/image/lv/1/PP_VP_L/louis-vuitton-ダミエデニム-スケートパンツ-プレタポルテ-洋服--HSD48WGRT650_PM2_Front view.jpg?wid={IMG_WIDTH}&hei={IMG_HEIGHT}",
          "@type": "ImageObject",
          "name": "Front view",
          "@context": "http://schema.org"
        },
        {
          "contentUrl": "https://jp.louisvuitton.com/images/is/image/lv/1/PP_VP_L/louis-vuitton-ダミエデニム-スケートパンツ-プレタポルテ-洋服--HSD48WGRT650_PM1_Side view.jpg?wid={IMG_WIDTH}&hei={IMG_HEIGHT}",
          "@type": "ImageObject",
          "name": "Side view",
          "@context": "http://schema.org"
        },
        {
          "contentUrl": "https://jp.louisvuitton.com/images/is/image/lv/1/PP_VP_L/louis-vuitton-ダミエデニム-スケートパンツ-プレタポルテ-洋服--HSD48WGRT650_PM1_Back view.jpg?wid={IMG_WIDTH}&hei={IMG_HEIGHT}",
          "@type": "ImageObject",
          "name": "Back view",
          "@context": "http://schema.org"
        }
      ],
      "url": "/jpn-jp/products/damier-denim-skate-pants-nvprod6010130v",
      "sizeDisplayName": "32",
      "category": [
        {
          "@type": "Thing",
          "url": "/jpn-jp/men/_/N-t18ui4cq",
          "alternateName": "men",
          "name": "メンズ",
          "identifier": "homme"
        },
        {
          "@type": "Thing",
          "url": "/jpn-jp/men/ready-to-wear/_/N-t1b9f3zb",
          "alternateName": "ready-to-wear",
          "name": "プレタポルテ(洋服)",
          "identifier": "m-readytowear"
        },
        {
          "@type": "Thing",
          "url": "/jpn-jp/men/ready-to-wear/denim/_/N-tgmiooy",
          "alternateName": "denim",
          "name": "メンズ デニム",
          "identifier": "m-denim-mrtw"
        }
      ],
      "additionalProperty": [
        {
          "@type": "PropertyValue",
          "name": "colorIconURL",
          "value": "https://jp.louisvuitton.com/images/is/image/lv/1/LV/louis-vuitton--MKC-RTW-650_indigo.jpg"
        },
        {
          "@type": "PropertyValue",
          "name": "detailedDescription",
          "value": "<ul><li>レギュラーフィット</li><li>カラー：インディゴ</li><li>本体：コットン 91%、ポリエステル 8%、ポリウレタン 1%</li><li>ジャカード織りのシグネチャー</li><li>ヴィンテージ風ゴールドカラーのドーム型ボタン</li><li>ヴィンテージ風ゴールドカラーのリベット</li><li>クラシックな5ポケットデニム</li><li>ヌバックのシグネチャーのジャクロンパッチ</li><li>イタリア製</li></ul>"
        },
        {
          "@type": "PropertyValue",
          "name": "englishProductName",
          "value": "Damier Denim Skate Pants   "
        },
        {
          "@type": "PropertyValue",
          "name": "activateEngraving",
          "value": false
        },
        {
          "@type": "PropertyValue",
          "name": "sellable",
          "value": true
        },
        {
          "@type": "PropertyValue",
          "name": "cscSellable",
          "value": true
        },
        {
          "@type": "PropertyValue",
          "name": "mom",
          "value": false
        },
        {
          "@type": "PropertyValue",
          "name": "locateInStore",
          "value": true
        },
        {
          "@type": "PropertyValue",
          "name": "materialGroupCode",
          "value": "Z05"
        },
        {
          "@type": "PropertyValue",
          "name": "filterCategories",
          "value": "Ready_To_Wear_Men"
        },
        {
          "@type": "PropertyValue",
          "name": "backOrderDisclaimer",
          "value": true
        },
        {
          "@type": "PropertyValue",
          "name": "backOrderFullDeposit",
          "value": false
        },
        {
          "@type": "PropertyValue",
          "name": "diamondEngravingEnabled",
          "value": false
        },
        {
          "@type": "PropertyValue",
          "name": "tryOnEnabled",
          "value": false
        },
        {
          "@type": "PropertyValue",
          "name": "video360Enabled",
          "value": false
        },
        {
          "@type": "PropertyValue",
          "name": "isBundle",
          "value": false
        },
        {
          "@type": "PropertyValue",
          "name": "eligibleToAgec",
          "value": true
        },
        {
          "@type": "PropertyValue",
          "name": "hasLanguagePanel",
          "value": false
        },
        {
          "@type": "PropertyValue",
          "name": "bannerList",
          "value": [
            {
              "commercialBanner": "top_banner_content_category_1"
            },
            {
              "commercialBanner": "top_banner_content_category_2"
            },
            {
              "commercialBanner": "top_banner_content_category_3"
            },
            {
              "commercialBanner": "top_banner_content_category_4"
            }
          ]
        }
      ],
      "careLink": {
        "sections": []
      },
      "collectibles": false,
      "identifier": "1AHCOF",
      "defaultFamilySapDisplayName": "PANTS DENIM M",
      "productVisible": true,
      "name": "ダミエデニム スケートパンツ",
      "packagingVariation": "",
      "highEndTemplate": false,
      "productId": "nvprod6010130v",
      "hasLanguagePanel": false,
      "disclaimers": {
        "customDisclaimer": false,
        "value": "dynamic_shipping_warning_bo",
        "popInContent": "dynamic_global_backorder_info_popin_content",
        "popInTitle": "dynamic_global_backorder_info_popin_title"
      },
      "color": "Indigo",
      "@context": "http://schema.org"
    },
    {
      "kitFlag": false,
      "_links": {
        "look": {
          "href": "/api/catalog/jpn-jp/skus/1AHCOG/look"
        },
        "parent": {
          "href": "/api/catalog/jpn-jp/product/nvprod6010130v"
        },
        "self": {
          "href": "/api/catalog/jpn-jp/product/1AHCOG"
        },
        "perso-details": {
          "href": "/api/catalog/jpn-jp/skus/1AHCOG/perso-detail"
        },
        "/api/rels/jpn-jp/add-to-cart-base/nvprod6010130v/1AHCOG/1": {
          "name": "add-to-cart",
          "href": "/api/cart/jpn-jp"
        }
      },
      "macroColor": "ブルー",
      "@type": "ProductModel",
      "identifierKey": "7bc1c70debbf1fb0300634b34a82cd1a",
      "productDetailTabs": [],
      "kitExclusivity": false,
      "offers": {
        "priceSpecification": {
          "priceCurrency": "JPY",
          "price": 317900
        },
        "@type": "Offer",
        "price": "¥317,900"
      },
      "disambiguatingDescription": "｢Marque L. Vuitton Déposée｣シグネチャーを組み合わせた柔らかな質感の3D ダミエ･ジャカードがデザインを引き立てる、エフォートレスなデニムスケートパンツ。ウォッシュ加工が施されたインディゴデニムをイエローのトップステッチとエイジング加工を施したゴールドカラーのメタルパーツで彩り、ウエストにはヌバックのダミエ･ジャクロンパッチをあしらいました。ミックス & マッチが楽しめるパンツを同シリーズのジャケットと組み合わせれば、個性的なコーディネートに。<br><br>ご不明な点がございましたら、クライアントサービスまでお気軽にお問合せください。専任のクライアントアドバイザーが、素材やサイズなどの製品詳細、モデル着用イメージや関連アイテムのご案内など、お客様のご要望に合わせたスタイリング・アドバイスをご提供いたします。<br>また、サイズ違いなどによる返品・交換のご相談も承ります。詳細は<a href='https://jp.louisvuitton.com/jpn-jp/legal-privacy'><b>こちら。</b></a>",
      "image": [
        {
          "contentUrl": "https://jp.louisvuitton.com/images/is/image/lv/1/PP_VP_L/louis-vuitton-ダミエデニム-スケートパンツ-プレタポルテ-洋服--HSD48WGRT650_PM2_Front view.jpg?wid={IMG_WIDTH}&hei={IMG_HEIGHT}",
          "@type": "ImageObject",
          "name": "Front view",
          "@context": "http://schema.org"
        },
        {
          "contentUrl": "https://jp.louisvuitton.com/images/is/image/lv/1/PP_VP_L/louis-vuitton-ダミエデニム-スケートパンツ-プレタポルテ-洋服--HSD48WGRT650_PM1_Side view.jpg?wid={IMG_WIDTH}&hei={IMG_HEIGHT}",
          "@type": "ImageObject",
          "name": "Side view",
          "@context": "http://schema.org"
        },
        {
          "contentUrl": "https://jp.louisvuitton.com/images/is/image/lv/1/PP_VP_L/louis-vuitton-ダミエデニム-スケートパンツ-プレタポルテ-洋服--HSD48WGRT650_PM1_Back view.jpg?wid={IMG_WIDTH}&hei={IMG_HEIGHT}",
          "@type": "ImageObject",
          "name": "Back view",
          "@context": "http://schema.org"
        }
      ],
      "url": "/jpn-jp/products/damier-denim-skate-pants-nvprod6010130v",
      "sizeDisplayName": "33",
      "category": [
        {
          "@type": "Thing",
          "url": "/jpn-jp/men/_/N-t18ui4cq",
          "alternateName": "men",
          "name": "メンズ",
          "identifier": "homme"
        },
        {
          "@type": "Thing",
          "url": "/jpn-jp/men/ready-to-wear/_/N-t1b9f3zb",
          "alternateName": "ready-to-wear",
          "name": "プレタポルテ(洋服)",
          "identifier": "m-readytowear"
        },
        {
          "@type": "Thing",
          "url": "/jpn-jp/men/ready-to-wear/denim/_/N-tgmiooy",
          "alternateName": "denim",
          "name": "メンズ デニム",
          "identifier": "m-denim-mrtw"
        }
      ],
      "additionalProperty": [
        {
          "@type": "PropertyValue",
          "name": "colorIconURL",
          "value": "https://jp.louisvuitton.com/images/is/image/lv/1/LV/louis-vuitton--MKC-RTW-650_indigo.jpg"
        },
        {
          "@type": "PropertyValue",
          "name": "detailedDescription",
          "value": "<ul><li>レギュラーフィット</li><li>カラー：インディゴ</li><li>本体：コットン 91%、ポリエステル 8%、ポリウレタン 1%</li><li>ジャカード織りのシグネチャー</li><li>ヴィンテージ風ゴールドカラーのドーム型ボタン</li><li>ヴィンテージ風ゴールドカラーのリベット</li><li>クラシックな5ポケットデニム</li><li>ヌバックのシグネチャーのジャクロンパッチ</li><li>イタリア製</li></ul>"
        },
        {
          "@type": "PropertyValue",
          "name": "englishProductName",
          "value": "Damier Denim Skate Pants   "
        },
        {
          "@type": "PropertyValue",
          "name": "activateEngraving",
          "value": false
        },
        {
          "@type": "PropertyValue",
          "name": "sellable",
          "value": true
        },
        {
          "@type": "PropertyValue",
          "name": "cscSellable",
          "value": true
        },
        {
          "@type": "PropertyValue",
          "name": "mom",
          "value": false
        },
        {
          "@type": "PropertyValue",
          "name": "locateInStore",
          "value": true
        },
        {
          "@type": "PropertyValue",
          "name": "materialGroupCode",
          "value": "Z05"
        },
        {
          "@type": "PropertyValue",
          "name": "filterCategories",
          "value": "Ready_To_Wear_Men"
        },
        {
          "@type": "PropertyValue",
          "name": "backOrderDisclaimer",
          "value": true
        },
        {
          "@type": "PropertyValue",
          "name": "backOrderFullDeposit",
          "value": false
        },
        {
          "@type": "PropertyValue",
          "name": "diamondEngravingEnabled",
          "value": false
        },
        {
          "@type": "PropertyValue",
          "name": "tryOnEnabled",
          "value": false
        },
        {
          "@type": "PropertyValue",
          "name": "video360Enabled",
          "value": false
        },
        {
          "@type": "PropertyValue",
          "name": "isBundle",
          "value": false
        },
        {
          "@type": "PropertyValue",
          "name": "eligibleToAgec",
          "value": true
        },
        {
          "@type": "PropertyValue",
          "name": "hasLanguagePanel",
          "value": false
        },
        {
          "@type": "PropertyValue",
          "name": "bannerList",
          "value": [
            {
              "commercialBanner": "top_banner_content_category_1"
            },
            {
              "commercialBanner": "top_banner_content_category_2"
            },
            {
              "commercialBanner": "top_banner_content_category_3"
            },
            {
              "commercialBanner": "top_banner_content_category_4"
            }
          ]
        }
      ],
      "careLink": {
        "sections": []
      },
      "collectibles": false,
      "identifier": "1AHCOG",
      "defaultFamilySapDisplayName": "PANTS DENIM M",
      "productVisible": true,
      "name": "ダミエデニム スケートパンツ",
      "packagingVariation": "",
      "highEndTemplate": false,
      "productId": "nvprod6010130v",
      "hasLanguagePanel": false,
      "disclaimers": {
        "customDisclaimer": false,
        "value": "dynamic_shipping_warning_bo",
        "popInContent": "dynamic_global_backorder_info_popin_content",
        "popInTitle": "dynamic_global_backorder_info_popin_title"
      },
      "color": "Indigo",
      "@context": "http://schema.org"
    },
    {
      "kitFlag": false,
      "_links": {
        "look": {
          "href": "/api/catalog/jpn-jp/skus/1AHCOH/look"
        },
        "parent": {
          "href": "/api/catalog/jpn-jp/product/nvprod6010130v"
        },
        "self": {
          "href": "/api/catalog/jpn-jp/product/1AHCOH"
        },
        "perso-details": {
          "href": "/api/catalog/jpn-jp/skus/1AHCOH/perso-detail"
        },
        "/api/rels/jpn-jp/add-to-cart-base/nvprod6010130v/1AHCOH/1": {
          "name": "add-to-cart",
          "href": "/api/cart/jpn-jp"
        }
      },
      "macroColor": "ブルー",
      "@type": "ProductModel",
      "identifierKey": "589ae092eedb5318ed8e53b472f4ec55",
      "productDetailTabs": [],
      "kitExclusivity": false,
      "offers": {
        "priceSpecification": {
          "priceCurrency": "JPY",
          "price": 317900
        },
        "@type": "Offer",
        "price": "¥317,900"
      },
      "disambiguatingDescription": "｢Marque L. Vuitton Déposée｣シグネチャーを組み合わせた柔らかな質感の3D ダミエ･ジャカードがデザインを引き立てる、エフォートレスなデニムスケートパンツ。ウォッシュ加工が施されたインディゴデニムをイエローのトップステッチとエイジング加工を施したゴールドカラーのメタルパーツで彩り、ウエストにはヌバックのダミエ･ジャクロンパッチをあしらいました。ミックス & マッチが楽しめるパンツを同シリーズのジャケットと組み合わせれば、個性的なコーディネートに。<br><br>ご不明な点がございましたら、クライアントサービスまでお気軽にお問合せください。専任のクライアントアドバイザーが、素材やサイズなどの製品詳細、モデル着用イメージや関連アイテムのご案内など、お客様のご要望に合わせたスタイリング・アドバイスをご提供いたします。<br>また、サイズ違いなどによる返品・交換のご相談も承ります。詳細は<a href='https://jp.louisvuitton.com/jpn-jp/legal-privacy'><b>こちら。</b></a>",
      "image": [
        {
          "contentUrl": "https://jp.louisvuitton.com/images/is/image/lv/1/PP_VP_L/louis-vuitton-ダミエデニム-スケートパンツ-プレタポルテ-洋服--HSD48WGRT650_PM2_Front view.jpg?wid={IMG_WIDTH}&hei={IMG_HEIGHT}",
          "@type": "ImageObject",
          "name": "Front view",
          "@context": "http://schema.org"
        },
        {
          "contentUrl": "https://jp.louisvuitton.com/images/is/image/lv/1/PP_VP_L/louis-vuitton-ダミエデニム-スケートパンツ-プレタポルテ-洋服--HSD48WGRT650_PM1_Side view.jpg?wid={IMG_WIDTH}&hei={IMG_HEIGHT}",
          "@type": "ImageObject",
          "name": "Side view",
          "@context": "http://schema.org"
        },
        {
          "contentUrl": "https://jp.louisvuitton.com/images/is/image/lv/1/PP_VP_L/louis-vuitton-ダミエデニム-スケートパンツ-プレタポルテ-洋服--HSD48WGRT650_PM1_Back view.jpg?wid={IMG_WIDTH}&hei={IMG_HEIGHT}",
          "@type": "ImageObject",
          "name": "Back view",
          "@context": "http://schema.org"
        }
      ],
      "url": "/jpn-jp/products/damier-denim-skate-pants-nvprod6010130v",
      "sizeDisplayName": "34",
      "category": [
        {
          "@type": "Thing",
          "url": "/jpn-jp/men/_/N-t18ui4cq",
          "alternateName": "men",
          "name": "メンズ",
          "identifier": "homme"
        },
        {
          "@type": "Thing",
          "url": "/jpn-jp/men/ready-to-wear/_/N-t1b9f3zb",
          "alternateName": "ready-to-wear",
          "name": "プレタポルテ(洋服)",
          "identifier": "m-readytowear"
        },
        {
          "@type": "Thing",
          "url": "/jpn-jp/men/ready-to-wear/denim/_/N-tgmiooy",
          "alternateName": "denim",
          "name": "メンズ デニム",
          "identifier": "m-denim-mrtw"
        }
      ],
      "additionalProperty": [
        {
          "@type": "PropertyValue",
          "name": "colorIconURL",
          "value": "https://jp.louisvuitton.com/images/is/image/lv/1/LV/louis-vuitton--MKC-RTW-650_indigo.jpg"
        },
        {
          "@type": "PropertyValue",
          "name": "detailedDescription",
          "value": "<ul><li>レギュラーフィット</li><li>カラー：インディゴ</li><li>本体：コットン 91%、ポリエステル 8%、ポリウレタン 1%</li><li>ジャカード織りのシグネチャー</li><li>ヴィンテージ風ゴールドカラーのドーム型ボタン</li><li>ヴィンテージ風ゴールドカラーのリベット</li><li>クラシックな5ポケットデニム</li><li>ヌバックのシグネチャーのジャクロンパッチ</li><li>イタリア製</li></ul>"
        },
        {
          "@type": "PropertyValue",
          "name": "englishProductName",
          "value": "Damier Denim Skate Pants   "
        },
        {
          "@type": "PropertyValue",
          "name": "activateEngraving",
          "value": false
        },
        {
          "@type": "PropertyValue",
          "name": "sellable",
          "value": true
        },
        {
          "@type": "PropertyValue",
          "name": "cscSellable",
          "value": true
        },
        {
          "@type": "PropertyValue",
          "name": "mom",
          "value": false
        },
        {
          "@type": "PropertyValue",
          "name": "locateInStore",
          "value": true
        },
        {
          "@type": "PropertyValue",
          "name": "materialGroupCode",
          "value": "Z05"
        },
        {
          "@type": "PropertyValue",
          "name": "filterCategories",
          "value": "Ready_To_Wear_Men"
        },
        {
          "@type": "PropertyValue",
          "name": "backOrderDisclaimer",
          "value": true
        },
        {
          "@type": "PropertyValue",
          "name": "backOrderFullDeposit",
          "value": false
        },
        {
          "@type": "PropertyValue",
          "name": "diamondEngravingEnabled",
          "value": false
        },
        {
          "@type": "PropertyValue",
          "name": "tryOnEnabled",
          "value": false
        },
        {
          "@type": "PropertyValue",
          "name": "video360Enabled",
          "value": false
        },
        {
          "@type": "PropertyValue",
          "name": "isBundle",
          "value": false
        },
        {
          "@type": "PropertyValue",
          "name": "eligibleToAgec",
          "value": true
        },
        {
          "@type": "PropertyValue",
          "name": "hasLanguagePanel",
          "value": false
        },
        {
          "@type": "PropertyValue",
          "name": "bannerList",
          "value": [
            {
              "commercialBanner": "top_banner_content_category_1"
            },
            {
              "commercialBanner": "top_banner_content_category_2"
            },
            {
              "commercialBanner": "top_banner_content_category_3"
            },
            {
              "commercialBanner": "top_banner_content_category_4"
            }
          ]
        }
      ],
      "careLink": {
        "sections": []
      },
      "collectibles": false,
      "identifier": "1AHCOH",
      "defaultFamilySapDisplayName": "PANTS DENIM M",
      "productVisible": true,
      "name": "ダミエデニム スケートパンツ",
      "packagingVariation": "",
      "highEndTemplate": false,
      "productId": "nvprod6010130v",
      "hasLanguagePanel": false,
      "disclaimers": {
        "customDisclaimer": false,
        "value": "dynamic_shipping_warning_bo",
        "popInContent": "dynamic_global_backorder_info_popin_content",
        "popInTitle": "dynamic_global_backorder_info_popin_title"
      },
      "color": "Indigo",
      "@context": "http://schema.org"
    },
    {
      "kitFlag": false,
      "_links": {
        "look": {
          "href": "/api/catalog/jpn-jp/skus/1AHCOI/look"
        },
        "parent": {
          "href": "/api/catalog/jpn-jp/product/nvprod6010130v"
        },
        "self": {
          "href": "/api/catalog/jpn-jp/product/1AHCOI"
        },
        "perso-details": {
          "href": "/api/catalog/jpn-jp/skus/1AHCOI/perso-detail"
        },
        "/api/rels/jpn-jp/add-to-cart-base/nvprod6010130v/1AHCOI/1": {
          "name": "add-to-cart",
          "href": "/api/cart/jpn-jp"
        }
      },
      "macroColor": "ブルー",
      "@type": "ProductModel",
      "identifierKey": "f1ba74c56b95aeed51a6a6639b4ecfaa",
      "productDetailTabs": [],
      "kitExclusivity": false,
      "offers": {
        "priceSpecification": {
          "priceCurrency": "JPY",
          "price": 317900
        },
        "@type": "Offer",
        "price": "¥317,900"
      },
      "disambiguatingDescription": "｢Marque L. Vuitton Déposée｣シグネチャーを組み合わせた柔らかな質感の3D ダミエ･ジャカードがデザインを引き立てる、エフォートレスなデニムスケートパンツ。ウォッシュ加工が施されたインディゴデニムをイエローのトップステッチとエイジング加工を施したゴールドカラーのメタルパーツで彩り、ウエストにはヌバックのダミエ･ジャクロンパッチをあしらいました。ミックス & マッチが楽しめるパンツを同シリーズのジャケットと組み合わせれば、個性的なコーディネートに。<br><br>ご不明な点がございましたら、クライアントサービスまでお気軽にお問合せください。専任のクライアントアドバイザーが、素材やサイズなどの製品詳細、モデル着用イメージや関連アイテムのご案内など、お客様のご要望に合わせたスタイリング・アドバイスをご提供いたします。<br>また、サイズ違いなどによる返品・交換のご相談も承ります。詳細は<a href='https://jp.louisvuitton.com/jpn-jp/legal-privacy'><b>こちら。</b></a>",
      "image": [
        {
          "contentUrl": "https://jp.louisvuitton.com/images/is/image/lv/1/PP_VP_L/louis-vuitton-ダミエデニム-スケートパンツ-プレタポルテ-洋服--HSD48WGRT650_PM2_Front view.jpg?wid={IMG_WIDTH}&hei={IMG_HEIGHT}",
          "@type": "ImageObject",
          "name": "Front view",
          "@context": "http://schema.org"
        },
        {
          "contentUrl": "https://jp.louisvuitton.com/images/is/image/lv/1/PP_VP_L/louis-vuitton-ダミエデニム-スケートパンツ-プレタポルテ-洋服--HSD48WGRT650_PM1_Side view.jpg?wid={IMG_WIDTH}&hei={IMG_HEIGHT}",
          "@type": "ImageObject",
          "name": "Side view",
          "@context": "http://schema.org"
        },
        {
          "contentUrl": "https://jp.louisvuitton.com/images/is/image/lv/1/PP_VP_L/louis-vuitton-ダミエデニム-スケートパンツ-プレタポルテ-洋服--HSD48WGRT650_PM1_Back view.jpg?wid={IMG_WIDTH}&hei={IMG_HEIGHT}",
          "@type": "ImageObject",
          "name": "Back view",
          "@context": "http://schema.org"
        }
      ],
      "url": "/jpn-jp/products/damier-denim-skate-pants-nvprod6010130v",
      "sizeDisplayName": "36",
      "category": [
        {
          "@type": "Thing",
          "url": "/jpn-jp/men/_/N-t18ui4cq",
          "alternateName": "men",
          "name": "メンズ",
          "identifier": "homme"
        },
        {
          "@type": "Thing",
          "url": "/jpn-jp/men/ready-to-wear/_/N-t1b9f3zb",
          "alternateName": "ready-to-wear",
          "name": "プレタポルテ(洋服)",
          "identifier": "m-readytowear"
        },
        {
          "@type": "Thing",
          "url": "/jpn-jp/men/ready-to-wear/denim/_/N-tgmiooy",
          "alternateName": "denim",
          "name": "メンズ デニム",
          "identifier": "m-denim-mrtw"
        }
      ],
      "additionalProperty": [
        {
          "@type": "PropertyValue",
          "name": "colorIconURL",
          "value": "https://jp.louisvuitton.com/images/is/image/lv/1/LV/louis-vuitton--MKC-RTW-650_indigo.jpg"
        },
        {
          "@type": "PropertyValue",
          "name": "detailedDescription",
          "value": "<ul><li>レギュラーフィット</li><li>カラー：インディゴ</li><li>本体：コットン 91%、ポリエステル 8%、ポリウレタン 1%</li><li>ジャカード織りのシグネチャー</li><li>ヴィンテージ風ゴールドカラーのドーム型ボタン</li><li>ヴィンテージ風ゴールドカラーのリベット</li><li>クラシックな5ポケットデニム</li><li>ヌバックのシグネチャーのジャクロンパッチ</li><li>イタリア製</li></ul>"
        },
        {
          "@type": "PropertyValue",
          "name": "englishProductName",
          "value": "Damier Denim Skate Pants   "
        },
        {
          "@type": "PropertyValue",
          "name": "activateEngraving",
          "value": false
        },
        {
          "@type": "PropertyValue",
          "name": "sellable",
          "value": true
        },
        {
          "@type": "PropertyValue",
          "name": "cscSellable",
          "value": true
        },
        {
          "@type": "PropertyValue",
          "name": "mom",
          "value": false
        },
        {
          "@type": "PropertyValue",
          "name": "locateInStore",
          "value": true
        },
        {
          "@type": "PropertyValue",
          "name": "materialGroupCode",
          "value": "Z05"
        },
        {
          "@type": "PropertyValue",
          "name": "filterCategories",
          "value": "Ready_To_Wear_Men"
        },
        {
          "@type": "PropertyValue",
          "name": "backOrderDisclaimer",
          "value": true
        },
        {
          "@type": "PropertyValue",
          "name": "backOrderFullDeposit",
          "value": false
        },
        {
          "@type": "PropertyValue",
          "name": "diamondEngravingEnabled",
          "value": false
        },
        {
          "@type": "PropertyValue",
          "name": "tryOnEnabled",
          "value": false
        },
        {
          "@type": "PropertyValue",
          "name": "video360Enabled",
          "value": false
        },
        {
          "@type": "PropertyValue",
          "name": "isBundle",
          "value": false
        },
        {
          "@type": "PropertyValue",
          "name": "eligibleToAgec",
          "value": true
        },
        {
          "@type": "PropertyValue",
          "name": "hasLanguagePanel",
          "value": false
        },
        {
          "@type": "PropertyValue",
          "name": "bannerList",
          "value": [
            {
              "commercialBanner": "top_banner_content_category_1"
            },
            {
              "commercialBanner": "top_banner_content_category_2"
            },
            {
              "commercialBanner": "top_banner_content_category_3"
            },
            {
              "commercialBanner": "top_banner_content_category_4"
            }
          ]
        }
      ],
      "careLink": {
        "sections": []
      },
      "collectibles": false,
      "identifier": "1AHCOI",
      "defaultFamilySapDisplayName": "PANTS DENIM M",
      "productVisible": true,
      "name": "ダミエデニム スケートパンツ",
      "packagingVariation": "",
      "highEndTemplate": false,
      "productId": "nvprod6010130v",
      "hasLanguagePanel": false,
      "disclaimers": {
        "customDisclaimer": false,
        "value": "dynamic_shipping_warning_bo",
        "popInContent": "dynamic_global_backorder_info_popin_content",
        "popInTitle": "dynamic_global_backorder_info_popin_title"
      },
      "color": "Indigo",
      "@context": "http://schema.org"
    },
    {
      "kitFlag": false,
      "_links": {
        "look": {
          "href": "/api/catalog/jpn-jp/skus/1AHCOJ/look"
        },
        "parent": {
          "href": "/api/catalog/jpn-jp/product/nvprod6010130v"
        },
        "self": {
          "href": "/api/catalog/jpn-jp/product/1AHCOJ"
        },
        "perso-details": {
          "href": "/api/catalog/jpn-jp/skus/1AHCOJ/perso-detail"
        },
        "/api/rels/jpn-jp/add-to-cart-base/nvprod6010130v/1AHCOJ/1": {
          "name": "add-to-cart",
          "href": "/api/cart/jpn-jp"
        }
      },
      "macroColor": "ブルー",
      "@type": "ProductModel",
      "identifierKey": "64b542abec15f2f673efb0a359322b6d",
      "productDetailTabs": [],
      "kitExclusivity": false,
      "offers": {
        "priceSpecification": {
          "priceCurrency": "JPY",
          "price": 317900
        },
        "@type": "Offer",
        "price": "¥317,900"
      },
      "disambiguatingDescription": "｢Marque L. Vuitton Déposée｣シグネチャーを組み合わせた柔らかな質感の3D ダミエ･ジャカードがデザインを引き立てる、エフォートレスなデニムスケートパンツ。ウォッシュ加工が施されたインディゴデニムをイエローのトップステッチとエイジング加工を施したゴールドカラーのメタルパーツで彩り、ウエストにはヌバックのダミエ･ジャクロンパッチをあしらいました。ミックス & マッチが楽しめるパンツを同シリーズのジャケットと組み合わせれば、個性的なコーディネートに。<br><br>ご不明な点がございましたら、クライアントサービスまでお気軽にお問合せください。専任のクライアントアドバイザーが、素材やサイズなどの製品詳細、モデル着用イメージや関連アイテムのご案内など、お客様のご要望に合わせたスタイリング・アドバイスをご提供いたします。<br>また、サイズ違いなどによる返品・交換のご相談も承ります。詳細は<a href='https://jp.louisvuitton.com/jpn-jp/legal-privacy'><b>こちら。</b></a>",
      "image": [
        {
          "contentUrl": "https://jp.louisvuitton.com/images/is/image/lv/1/PP_VP_L/louis-vuitton-ダミエデニム-スケートパンツ-プレタポルテ-洋服--HSD48WGRT650_PM2_Front view.jpg?wid={IMG_WIDTH}&hei={IMG_HEIGHT}",
          "@type": "ImageObject",
          "name": "Front view",
          "@context": "http://schema.org"
        },
        {
          "contentUrl": "https://jp.louisvuitton.com/images/is/image/lv/1/PP_VP_L/louis-vuitton-ダミエデニム-スケートパンツ-プレタポルテ-洋服--HSD48WGRT650_PM1_Side view.jpg?wid={IMG_WIDTH}&hei={IMG_HEIGHT}",
          "@type": "ImageObject",
          "name": "Side view",
          "@context": "http://schema.org"
        },
        {
          "contentUrl": "https://jp.louisvuitton.com/images/is/image/lv/1/PP_VP_L/louis-vuitton-ダミエデニム-スケートパンツ-プレタポルテ-洋服--HSD48WGRT650_PM1_Back view.jpg?wid={IMG_WIDTH}&hei={IMG_HEIGHT}",
          "@type": "ImageObject",
          "name": "Back view",
          "@context": "http://schema.org"
        }
      ],
      "url": "/jpn-jp/products/damier-denim-skate-pants-nvprod6010130v",
      "sizeDisplayName": "38",
      "category": [
        {
          "@type": "Thing",
          "url": "/jpn-jp/men/_/N-t18ui4cq",
          "alternateName": "men",
          "name": "メンズ",
          "identifier": "homme"
        },
        {
          "@type": "Thing",
          "url": "/jpn-jp/men/ready-to-wear/_/N-t1b9f3zb",
          "alternateName": "ready-to-wear",
          "name": "プレタポルテ(洋服)",
          "identifier": "m-readytowear"
        },
        {
          "@type": "Thing",
          "url": "/jpn-jp/men/ready-to-wear/denim/_/N-tgmiooy",
          "alternateName": "denim",
          "name": "メンズ デニム",
          "identifier": "m-denim-mrtw"
        }
      ],
      "additionalProperty": [
        {
          "@type": "PropertyValue",
          "name": "colorIconURL",
          "value": "https://jp.louisvuitton.com/images/is/image/lv/1/LV/louis-vuitton--MKC-RTW-650_indigo.jpg"
        },
        {
          "@type": "PropertyValue",
          "name": "detailedDescription",
          "value": "<ul><li>レギュラーフィット</li><li>カラー：インディゴ</li><li>本体：コットン 91%、ポリエステル 8%、ポリウレタン 1%</li><li>ジャカード織りのシグネチャー</li><li>ヴィンテージ風ゴールドカラーのドーム型ボタン</li><li>ヴィンテージ風ゴールドカラーのリベット</li><li>クラシックな5ポケットデニム</li><li>ヌバックのシグネチャーのジャクロンパッチ</li><li>イタリア製</li></ul>"
        },
        {
          "@type": "PropertyValue",
          "name": "englishProductName",
          "value": "Damier Denim Skate Pants   "
        },
        {
          "@type": "PropertyValue",
          "name": "activateEngraving",
          "value": false
        },
        {
          "@type": "PropertyValue",
          "name": "sellable",
          "value": true
        },
        {
          "@type": "PropertyValue",
          "name": "cscSellable",
          "value": true
        },
        {
          "@type": "PropertyValue",
          "name": "mom",
          "value": false
        },
        {
          "@type": "PropertyValue",
          "name": "locateInStore",
          "value": true
        },
        {
          "@type": "PropertyValue",
          "name": "materialGroupCode",
          "value": "Z05"
        },
        {
          "@type": "PropertyValue",
          "name": "filterCategories",
          "value": "Ready_To_Wear_Men"
        },
        {
          "@type": "PropertyValue",
          "name": "backOrderDisclaimer",
          "value": true
        },
        {
          "@type": "PropertyValue",
          "name": "backOrderFullDeposit",
          "value": false
        },
        {
          "@type": "PropertyValue",
          "name": "diamondEngravingEnabled",
          "value": false
        },
        {
          "@type": "PropertyValue",
          "name": "tryOnEnabled",
          "value": false
        },
        {
          "@type": "PropertyValue",
          "name": "video360Enabled",
          "value": false
        },
        {
          "@type": "PropertyValue",
          "name": "isBundle",
          "value": false
        },
        {
          "@type": "PropertyValue",
          "name": "eligibleToAgec",
          "value": true
        },
        {
          "@type": "PropertyValue",
          "name": "hasLanguagePanel",
          "value": false
        },
        {
          "@type": "PropertyValue",
          "name": "bannerList",
          "value": [
            {
              "commercialBanner": "top_banner_content_category_1"
            },
            {
              "commercialBanner": "top_banner_content_category_2"
            },
            {
              "commercialBanner": "top_banner_content_category_3"
            },
            {
              "commercialBanner": "top_banner_content_category_4"
            }
          ]
        }
      ],
      "careLink": {
        "sections": []
      },
      "collectibles": false,
      "identifier": "1AHCOJ",
      "defaultFamilySapDisplayName": "PANTS DENIM M",
      "productVisible": true,
      "name": "ダミエデニム スケートパンツ",
      "packagingVariation": "",
      "highEndTemplate": false,
      "productId": "nvprod6010130v",
      "hasLanguagePanel": false,
      "disclaimers": {
        "customDisclaimer": false,
        "value": "dynamic_shipping_warning_bo",
        "popInContent": "dynamic_global_backorder_info_popin_content",
        "popInTitle": "dynamic_global_backorder_info_popin_title"
      },
      "color": "Indigo",
      "@context": "http://schema.org"
    },
    {
      "kitFlag": false,
      "_links": {
        "look": {
          "href": "/api/catalog/jpn-jp/skus/1AHCOK/look"
        },
        "parent": {
          "href": "/api/catalog/jpn-jp/product/nvprod6010130v"
        },
        "self": {
          "href": "/api/catalog/jpn-jp/product/1AHCOK"
        },
        "perso-details": {
          "href": "/api/catalog/jpn-jp/skus/1AHCOK/perso-detail"
        },
        "/api/rels/jpn-jp/add-to-cart-base/nvprod6010130v/1AHCOK/1": {
          "name": "add-to-cart",
          "href": "/api/cart/jpn-jp"
        }
      },
      "macroColor": "ブルー",
      "@type": "ProductModel",
      "identifierKey": "d69cf222cc19083b6a392c5f0acb3127",
      "productDetailTabs": [],
      "kitExclusivity": false,
      "offers": {
        "priceSpecification": {
          "priceCurrency": "JPY",
          "price": 317900
        },
        "@type": "Offer",
        "price": "¥317,900"
      },
      "disambiguatingDescription": "｢Marque L. Vuitton Déposée｣シグネチャーを組み合わせた柔らかな質感の3D ダミエ･ジャカードがデザインを引き立てる、エフォートレスなデニムスケートパンツ。ウォッシュ加工が施されたインディゴデニムをイエローのトップステッチとエイジング加工を施したゴールドカラーのメタルパーツで彩り、ウエストにはヌバックのダミエ･ジャクロンパッチをあしらいました。ミックス & マッチが楽しめるパンツを同シリーズのジャケットと組み合わせれば、個性的なコーディネートに。<br><br>ご不明な点がございましたら、クライアントサービスまでお気軽にお問合せください。専任のクライアントアドバイザーが、素材やサイズなどの製品詳細、モデル着用イメージや関連アイテムのご案内など、お客様のご要望に合わせたスタイリング・アドバイスをご提供いたします。<br>また、サイズ違いなどによる返品・交換のご相談も承ります。詳細は<a href='https://jp.louisvuitton.com/jpn-jp/legal-privacy'><b>こちら。</b></a>",
      "image": [
        {
          "contentUrl": "https://jp.louisvuitton.com/images/is/image/lv/1/PP_VP_L/louis-vuitton-ダミエデニム-スケートパンツ-プレタポルテ-洋服--HSD48WGRT650_PM2_Front view.jpg?wid={IMG_WIDTH}&hei={IMG_HEIGHT}",
          "@type": "ImageObject",
          "name": "Front view",
          "@context": "http://schema.org"
        },
        {
          "contentUrl": "https://jp.louisvuitton.com/images/is/image/lv/1/PP_VP_L/louis-vuitton-ダミエデニム-スケートパンツ-プレタポルテ-洋服--HSD48WGRT650_PM1_Side view.jpg?wid={IMG_WIDTH}&hei={IMG_HEIGHT}",
          "@type": "ImageObject",
          "name": "Side view",
          "@context": "http://schema.org"
        },
        {
          "contentUrl": "https://jp.louisvuitton.com/images/is/image/lv/1/PP_VP_L/louis-vuitton-ダミエデニム-スケートパンツ-プレタポルテ-洋服--HSD48WGRT650_PM1_Back view.jpg?wid={IMG_WIDTH}&hei={IMG_HEIGHT}",
          "@type": "ImageObject",
          "name": "Back view",
          "@context": "http://schema.org"
        }
      ],
      "url": "/jpn-jp/products/damier-denim-skate-pants-nvprod6010130v",
      "sizeDisplayName": "40",
      "category": [
        {
          "@type": "Thing",
          "url": "/jpn-jp/men/_/N-t18ui4cq",
          "alternateName": "men",
          "name": "メンズ",
          "identifier": "homme"
        },
        {
          "@type": "Thing",
          "url": "/jpn-jp/men/ready-to-wear/_/N-t1b9f3zb",
          "alternateName": "ready-to-wear",
          "name": "プレタポルテ(洋服)",
          "identifier": "m-readytowear"
        },
        {
          "@type": "Thing",
          "url": "/jpn-jp/men/ready-to-wear/denim/_/N-tgmiooy",
          "alternateName": "denim",
          "name": "メンズ デニム",
          "identifier": "m-denim-mrtw"
        }
      ],
      "additionalProperty": [
        {
          "@type": "PropertyValue",
          "name": "colorIconURL",
          "value": "https://jp.louisvuitton.com/images/is/image/lv/1/LV/louis-vuitton--MKC-RTW-650_indigo.jpg"
        },
        {
          "@type": "PropertyValue",
          "name": "detailedDescription",
          "value": "<ul><li>レギュラーフィット</li><li>カラー：インディゴ</li><li>本体：コットン 91%、ポリエステル 8%、ポリウレタン 1%</li><li>ジャカード織りのシグネチャー</li><li>ヴィンテージ風ゴールドカラーのドーム型ボタン</li><li>ヴィンテージ風ゴールドカラーのリベット</li><li>クラシックな5ポケットデニム</li><li>ヌバックのシグネチャーのジャクロンパッチ</li><li>イタリア製</li></ul>"
        },
        {
          "@type": "PropertyValue",
          "name": "englishProductName",
          "value": "Damier Denim Skate Pants   "
        },
        {
          "@type": "PropertyValue",
          "name": "activateEngraving",
          "value": false
        },
        {
          "@type": "PropertyValue",
          "name": "sellable",
          "value": true
        },
        {
          "@type": "PropertyValue",
          "name": "cscSellable",
          "value": true
        },
        {
          "@type": "PropertyValue",
          "name": "mom",
          "value": false
        },
        {
          "@type": "PropertyValue",
          "name": "locateInStore",
          "value": true
        },
        {
          "@type": "PropertyValue",
          "name": "materialGroupCode",
          "value": "Z05"
        },
        {
          "@type": "PropertyValue",
          "name": "filterCategories",
          "value": "Ready_To_Wear_Men"
        },
        {
          "@type": "PropertyValue",
          "name": "backOrderDisclaimer",
          "value": true
        },
        {
          "@type": "PropertyValue",
          "name": "backOrderFullDeposit",
          "value": false
        },
        {
          "@type": "PropertyValue",
          "name": "diamondEngravingEnabled",
          "value": false
        },
        {
          "@type": "PropertyValue",
          "name": "tryOnEnabled",
          "value": false
        },
        {
          "@type": "PropertyValue",
          "name": "video360Enabled",
          "value": false
        },
        {
          "@type": "PropertyValue",
          "name": "isBundle",
          "value": false
        },
        {
          "@type": "PropertyValue",
          "name": "eligibleToAgec",
          "value": true
        },
        {
          "@type": "PropertyValue",
          "name": "hasLanguagePanel",
          "value": false
        },
        {
          "@type": "PropertyValue",
          "name": "bannerList",
          "value": [
            {
              "commercialBanner": "top_banner_content_category_1"
            },
            {
              "commercialBanner": "top_banner_content_category_2"
            },
            {
              "commercialBanner": "top_banner_content_category_3"
            },
            {
              "commercialBanner": "top_banner_content_category_4"
            }
          ]
        }
      ],
      "careLink": {
        "sections": []
      },
      "collectibles": false,
      "identifier": "1AHCOK",
      "defaultFamilySapDisplayName": "PANTS DENIM M",
      "productVisible": true,
      "name": "ダミエデニム スケートパンツ",
      "packagingVariation": "",
      "highEndTemplate": false,
      "productId": "nvprod6010130v",
      "hasLanguagePanel": false,
      "disclaimers": {
        "customDisclaimer": false,
        "value": "dynamic_shipping_warning_bo",
        "popInContent": "dynamic_global_backorder_info_popin_content",
        "popInTitle": "dynamic_global_backorder_info_popin_title"
      },
      "color": "Indigo",
      "@context": "http://schema.org"
    }
  ],
  "panelInformations": [
    {
      "@type": "ProductCare",
      "title": "素材とお手入れ方法、修理",
      "description": "<ul>\n  <li>家庭での洗濯禁止</li>\n  <li>塩素系および酸素系漂白剤は使用禁止</li>\n  <li>タンブル乾燥禁止</li>\n  <li>温度110℃以下でアイロン仕上げ可(スチームなし)</li>\n  <li>専門業者での弱流による炭化水素系のドライクリーニング溶剤使用可</li>\n  <li>弱流でのドライクリーニング可</li>\n  <li>ドライクリーニングの際は、裏返してネットに入れてください</li>\n  <li>アイロン掛けの際は、裏返しにしてあて布を使用してください</li>\n</ul>",
      "introduction": "<p>本製品のお手入れに際しては、次の取扱い表示をご確認いただき、末永くご愛用くださいますようお願い申しあげます。</p>"
    }
  ],
  "_links": {
    "self": {
      "href": "/api/catalog/jpn-jp/product/nvprod6010130v"
    },
    "push": {
      "href": "/api/catalog/jpn-jp/product-push/nvprod6010130v"
    },
    "care-link": {
      "href": "/api/catalog/jpn-jp/care-link/nvprod6010130v"
    },
    "size-guide": {
      "href": "/api/catalog/jpn-jp/size-guide/nvprod6010130v"
    },
    "availability": {
      "href": "/api/catalog/jpn-jp/availability/nvprod6010130v"
    }
  },
  "@type": "Product",
  "sku": "1AHCOD",
  "isSimilarTo": [],
  "productTips": [],
  "url": "/jpn-jp/products/damier-denim-skate-pants-nvprod6010130v",
  "category": [
    {
      "@type": "Thing",
      "url": "/jpn-jp/men/_/N-t18ui4cq",
      "alternateName": "men",
      "name": "メンズ",
      "identifier": "homme"
    },
    {
      "@type": "Thing",
      "url": "/jpn-jp/men/ready-to-wear/_/N-t1b9f3zb",
      "alternateName": "ready-to-wear",
      "name": "プレタポルテ(洋服)",
      "identifier": "m-readytowear"
    },
    {
      "@type": "Thing",
      "url": "/jpn-jp/men/ready-to-wear/denim/_/N-tgmiooy",
      "alternateName": "denim",
      "name": "メンズ デニム",
      "identifier": "m-denim-mrtw"
    }
  ],
  "additionalProperty": [
    {
      "@type": "PropertyValue",
      "name": "hidePrice",
      "value": false
    },
    {
      "@type": "PropertyValue",
      "name": "subType",
      "value": "product"
    },
    {
      "@type": "PropertyValue",
      "name": "sizeGuide",
      "value": true
    },
    {
      "@type": "PropertyValue",
      "name": "bannerList",
      "value": [
        {
          "commercialBanner": "top_banner_content_category_1"
        },
        {
          "commercialBanner": "top_banner_content_category_2"
        },
        {
          "commercialBanner": "top_banner_content_category_3"
        },
        {
          "commercialBanner": "top_banner_content_category_4"
        }
      ]
    }
  ],
  "name": "ダミエデニム スケートパンツ",
  "isRelatedTo": [],
  "@context": "http://schema.org",
  "identifier": "nvprod6010130v"
}
