{
  "model": [
    {
      "productVisible": true,
      "_links": {
        "look": {
          "href": "/api/catalog/jpn-jp/skus/nvsku3190004v/look"
        },
        "parent": {
          "href": "/api/catalog/jpn-jp/product/nvprod3660093v"
        },
        "self": {
          "href": "/api/catalog/jpn-jp/product/nvsku3190004v"
        },
        "perso-details": {
          "href": "/api/catalog/jpn-jp/skus/nvsku3190004v/perso-detail"
        },
        "/api/rels/jpn-jp/add-to-cart-base/nvprod3660093v/nvsku3190004v/1": {
          "name": "add-to-cart",
          "href": "/api/cart/jpn-jp"
        }
      },
      "@type": "ProductModel",
      "name": "LV MATCH - LOOK 03",
      "image": [
        {
          "contentUrl": "https://jp.louisvuitton.com/images/is/image/lv/1/PP_VP_L/louis-vuitton--Women_LVSet_FW22_LOOK03_VISUAL4.jpg?wid={IMG_WIDTH}&hei={IMG_HEIGHT}",
          "@type": "ImageObject",
          "name": "FW22",
          "@context": "http://schema.org"
        }
      ],
      "url": "/jpn-jp/products/lv-match-look-03-nvprod3660093v",
      "highEndTemplate": false,
      "productId": "nvprod3660093v",
      "additionalProperty": [
        {
          "@type": "PropertyValue",
          "name": "activateEngraving",
          "value": false
        },
        {
          "@type": "PropertyValue",
          "name": "sellable",
          "value": false
        },
        {
          "@type": "PropertyValue",
          "name": "cscSellable",
          "value": true
        },
        {
          "@type": "PropertyValue",
          "name": "mom",
          "value": false
        },
        {
          "@type": "PropertyValue",
          "name": "locateInStore",
          "value": true
        },
        {
          "@type": "PropertyValue",
          "name": "backOrderDisclaimer",
          "value": true
        },
        {
          "@type": "PropertyValue",
          "name": "backOrderFullDeposit",
          "value": false
        },
        {
          "@type": "PropertyValue",
          "name": "tryOnEnabled",
          "value": false
        },
        {
          "@type": "PropertyValue",
          "name": "isBundle",
          "value": false
        },
        {
          "@type": "PropertyValue",
          "name": "360ViewEnabled",
          "value": false
        }
      ],
      "category": [
        {
          "@type": "Thing",
          "url": "/jpn-jp/women/_/N-1q5sgib",
          "alternateName": "women",
          "name": "ウィメンズ",
          "identifier": "femme"
        },
        {
          "@type": "Thing",
          "url": "/jpn-jp/women/ready-to-wear/_/N-1nzqmbe",
          "alternateName": "ready-to-wear",
          "name": "プレタポルテ（洋服）",
          "identifier": "w-readytowear"
        },
        {
          "@type": "Thing",
          "url": "/jpn-jp/women/ready-to-wear/view-by-look/_/N-zazi08",
          "alternateName": "view-by-look",
          "name": "ルックブック",
          "identifier": "nvcat460115v"
        }
      ],
      "disclaimers": {
        "value": "shipping_warning_bo",
        "popInContent": "global_backorder_info_popin_content",
        "popInTitle": "global_backorder_info_popin_title"
      },
      "@context": "http://schema.org",
      "identifier": "nvsku3190004v"
    }
  ],
  "readyToWearSKUs": [
    {
      "productVisible": true,
      "_links": {
        "look": {
          "href": "/api/catalog/jpn-jp/skus/1AA8VN/look"
        },
        "parent": {
          "href": "/api/catalog/jpn-jp/product/nvprod3650004v"
        },
        "self": {
          "href": "/api/catalog/jpn-jp/product/1AA8VN"
        },
        "perso-details": {
          "href": "/api/catalog/jpn-jp/skus/1AA8VN/perso-detail"
        },
        "/api/rels/jpn-jp/add-to-cart-base/nvprod3650004v/1AA8VN/1": {
          "name": "add-to-cart",
          "href": "/api/cart/jpn-jp"
        }
      },
      "macroColor": "ブルー",
      "@type": "ProductModel",
      "name": "LVマッチポロトップ",
      "offers": {
        "priceSpecification": {
          "priceCurrency": "JPY",
          "price": 149600
        },
        "@type": "Offer",
        "price": "¥149,600"
      },
      "disambiguatingDescription": "「LV マッチ」カプセル･コレクションならではのエスプリでアップデートした、クラシカルなポロシャツ。タイムレスなデザインを柔らかで伸縮性のあるテクニカルジャージーで再解釈し、なめらかなコーティングを施したハーフファスナーでモダンなひねりを効かせました。襟元のシングルストライプがグラフィカルな印象をさりげなくプラスし、「Vuittamines(ヴィタミンズ)」カプセル･コレクションの雰囲気を伝える「LV Circle Vuitton」シグネチャーのラバー製のパッチが個性を放ちます。<p>ご不明な点がございましたら、クライアントサービスまでお気軽にお問合せください。専任のクライアントアドバイザーが、素材やサイズなどの製品詳細、モデル着用イメージや関連アイテムのご案内など、お客様のご要望に合わせたスタイリング・アドバイスをご提供いたします。</p><p>また、サイズ違いなどによる返品・交換のご相談も承ります。詳細は<a href=\"https://jp.louisvuitton.com/jpn-jp/legal-privacy\"><b>こちら。</b></a></p>",
      "image": [
        {
          "contentUrl": "https://jp.louisvuitton.com/images/is/image/lv/1/PP_VP_L/louis-vuitton-lvマッチポロトップ--FNBL46G72601_PM2_Front view.jpg?wid={IMG_WIDTH}&hei={IMG_HEIGHT}",
          "@type": "ImageObject",
          "name": "Front view",
          "@context": "http://schema.org"
        },
        {
          "contentUrl": "https://jp.louisvuitton.com/images/is/image/lv/1/PP_VP_L/louis-vuitton-lvマッチポロトップ--FNBL46G72601_PM1_Worn view.jpg?wid={IMG_WIDTH}&hei={IMG_HEIGHT}",
          "@type": "ImageObject",
          "name": "Worn view",
          "@context": "http://schema.org"
        },
        {
          "contentUrl": "https://jp.louisvuitton.com/images/is/image/lv/1/PP_VP_L/louis-vuitton-lvマッチポロトップ--FNBL46G72601_PM1_Ambiance view.jpg?wid={IMG_WIDTH}&hei={IMG_HEIGHT}",
          "@type": "ImageObject",
          "name": "Ambiance view",
          "@context": "http://schema.org"
        },
        {
          "contentUrl": "https://jp.louisvuitton.com/images/is/image/lv/1/PP_VP_L/louis-vuitton-lvマッチポロトップ--FNBL46G72601_PM1_Cropped view.jpg?wid={IMG_WIDTH}&hei={IMG_HEIGHT}",
          "@type": "ImageObject",
          "name": "Cropped view",
          "@context": "http://schema.org"
        },
        {
          "contentUrl": "https://jp.louisvuitton.com/images/is/image/lv/1/PP_VP_L/louis-vuitton-lvマッチポロトップ--FNBL46G72601_PM1_Cropped worn view.jpg?wid={IMG_WIDTH}&hei={IMG_HEIGHT}",
          "@type": "ImageObject",
          "name": "Cropped worn view",
          "@context": "http://schema.org"
        }
      ],
      "url": "/jpn-jp/products/lv-set-polo-top-nvprod3650004v",
      "highEndTemplate": false,
      "sizeDisplayName": "36",
      "productId": "nvprod3650004v",
      "additionalProperty": [
        {
          "@type": "PropertyValue",
          "name": "colorIconURL",
          "value": "https://jp.louisvuitton.com/images/is/image/lv/1/LV/louis-vuitton--MKC-RTW-601_bleu_glacier.jpg"
        },
        {
          "@type": "PropertyValue",
          "name": "detailedDescription",
          "value": "<ul><li>本体：ナイロン 72%、ポリウレタン 28%</li><li>その他：ナイロン 98%、ポリウレタン 2%</li><li>レギュラーフィット</li><li>モデル着用36サイズ</li><li>モデル：バスト 79cm、身長 175cm、ウエスト 59cm、ヒップ 87cm</li><li>イタリア製</li><li>家庭での洗濯禁止</li><li>塩素系および酸素系漂白剤の使用禁止</li><li>タンブル乾燥禁止</li><li>底面温度110℃を限度としてスチームなしでアイロン仕上げ可</li><li>石油系溶剤による弱いドライクリーニング可</li><li>REF：FNBL46G72</li></ul>"
        },
        {
          "@type": "PropertyValue",
          "name": "activateEngraving",
          "value": false
        },
        {
          "@type": "PropertyValue",
          "name": "sellable",
          "value": true
        },
        {
          "@type": "PropertyValue",
          "name": "cscSellable",
          "value": true
        },
        {
          "@type": "PropertyValue",
          "name": "mom",
          "value": false
        },
        {
          "@type": "PropertyValue",
          "name": "locateInStore",
          "value": true
        },
        {
          "@type": "PropertyValue",
          "name": "materialGroupCode",
          "value": "Z05"
        },
        {
          "@type": "PropertyValue",
          "name": "filterCategories",
          "value": "Ready_To_Wear_Women"
        },
        {
          "@type": "PropertyValue",
          "name": "backOrderDisclaimer",
          "value": true
        },
        {
          "@type": "PropertyValue",
          "name": "backOrderFullDeposit",
          "value": false
        },
        {
          "@type": "PropertyValue",
          "name": "tryOnEnabled",
          "value": false
        },
        {
          "@type": "PropertyValue",
          "name": "isBundle",
          "value": false
        },
        {
          "@type": "PropertyValue",
          "name": "360ViewEnabled",
          "value": false
        }
      ],
      "category": [
        {
          "@type": "Thing",
          "url": "/jpn-jp/women/_/N-1q5sgib",
          "alternateName": "women",
          "name": "ウィメンズ",
          "identifier": "femme"
        },
        {
          "@type": "Thing",
          "url": "/jpn-jp/women/ready-to-wear/_/N-1nzqmbe",
          "alternateName": "ready-to-wear",
          "name": "プレタポルテ（洋服）",
          "identifier": "w-readytowear"
        },
        {
          "@type": "Thing",
          "url": "/jpn-jp/women/ready-to-wear/tops/_/N-1miba2c",
          "alternateName": "tops",
          "name": "ウィメンズ トップス",
          "identifier": "w-tops"
        }
      ],
      "disclaimers": {
        "value": "shipping_warning_bo",
        "popInContent": "global_backorder_info_popin_content",
        "popInTitle": "global_backorder_info_popin_title"
      },
      "color": "ブルーグラシエール",
      "@context": "http://schema.org",
      "identifier": "1AA8VN"
    },
    {
      "productVisible": true,
      "_links": {
        "look": {
          "href": "/api/catalog/jpn-jp/skus/1AAA0Q/look"
        },
        "parent": {
          "href": "/api/catalog/jpn-jp/product/nvprod3670037v"
        },
        "self": {
          "href": "/api/catalog/jpn-jp/product/1AAA0Q"
        },
        "perso-details": {
          "href": "/api/catalog/jpn-jp/skus/1AAA0Q/perso-detail"
        },
        "/api/rels/jpn-jp/add-to-cart-base/nvprod3670037v/1AAA0Q/1": {
          "name": "add-to-cart",
          "href": "/api/cart/jpn-jp"
        }
      },
      "macroColor": "ホワイト",
      "@type": "ProductModel",
      "name": "テーラードテニスドレステニスミディスカート",
      "offers": {
        "priceSpecification": {
          "priceCurrency": "JPY",
          "price": 282700
        },
        "@type": "Offer",
        "price": "¥282,700"
      },
      "disambiguatingDescription": "伝統的なテニスウェアをエレガントにアップデートした、ミディアム丈のスカート。張りのある軽量なクレープを使用し、シルエットにエレガントな動きを生み出すスマートプリーツを施しました。洗練されたメタルボタンがウエストバンドにさりげない個性をプラスし、務歯見せのサイドファスナーがスポーティな印象を引き立てます。<p>ご不明な点がございましたら、クライアントサービスまでお気軽にお問合せください。専任のクライアントアドバイザーが、素材やサイズなどの製品詳細、モデル着用イメージや関連アイテムのご案内など、お客様のご要望に合わせたスタイリング・アドバイスをご提供いたします。</p><p>また、サイズ違いなどによる返品・交換のご相談も承ります。詳細は<a href=\"https://jp.louisvuitton.com/jpn-jp/legal-privacy\"><b>こちら。</b></a></p>",
      "image": [
        {
          "contentUrl": "https://jp.louisvuitton.com/images/is/image/lv/1/PP_VP_L/louis-vuitton-テーラードテニスドレステニスミディスカート--FNSK39FI3001_PM2_Front view.jpg?wid={IMG_WIDTH}&hei={IMG_HEIGHT}",
          "@type": "ImageObject",
          "name": "Front view",
          "@context": "http://schema.org"
        },
        {
          "contentUrl": "https://jp.louisvuitton.com/images/is/image/lv/1/PP_VP_L/louis-vuitton-テーラードテニスドレステニスミディスカート--FNSK39FI3001_PM1_Worn view.jpg?wid={IMG_WIDTH}&hei={IMG_HEIGHT}",
          "@type": "ImageObject",
          "name": "Worn view",
          "@context": "http://schema.org"
        },
        {
          "contentUrl": "https://jp.louisvuitton.com/images/is/image/lv/1/PP_VP_L/louis-vuitton-テーラードテニスドレステニスミディスカート--FNSK39FI3001_PM1_Side view.jpg?wid={IMG_WIDTH}&hei={IMG_HEIGHT}",
          "@type": "ImageObject",
          "name": "Side view",
          "@context": "http://schema.org"
        },
        {
          "contentUrl": "https://jp.louisvuitton.com/images/is/image/lv/1/PP_VP_L/louis-vuitton-テーラードテニスドレステニスミディスカート--FNSK39FI3001_PM1_Ambiance view.jpg?wid={IMG_WIDTH}&hei={IMG_HEIGHT}",
          "@type": "ImageObject",
          "name": "Ambiance view",
          "@context": "http://schema.org"
        },
        {
          "contentUrl": "https://jp.louisvuitton.com/images/is/image/lv/1/PP_VP_L/louis-vuitton-テーラードテニスドレステニスミディスカート--FNSK39FI3001_PM1_Cropped worn view.jpg?wid={IMG_WIDTH}&hei={IMG_HEIGHT}",
          "@type": "ImageObject",
          "name": "Cropped worn view",
          "@context": "http://schema.org"
        }
      ],
      "url": "/jpn-jp/products/tailored-tennis-midi-skirt-nvprod3670037v",
      "highEndTemplate": false,
      "sizeDisplayName": "36",
      "productId": "nvprod3670037v",
      "additionalProperty": [
        {
          "@type": "PropertyValue",
          "name": "colorIconURL",
          "value": "https://jp.louisvuitton.com/images/is/image/lv/1/LV/louis-vuitton--MKC-RTW-001_blanc.jpg"
        },
        {
          "@type": "PropertyValue",
          "name": "detailedDescription",
          "value": "<ul><li>長さ：80cm</li><li>表地：アセテート 53%、レーヨン 47%</li><li>裏地：レーヨン 53%、キュプラ 47%</li><li>レギュラーフィット</li><li>モデル着用36サイズ</li><li>モデル：バスト 79cm、身長 175cm、ウエスト 59cm、ヒップ 87cm</li><li>フランス製</li><li>家庭での洗濯禁止</li><li>塩素系および酸素系漂白剤の使用禁止</li><li>タンブル乾燥禁止</li><li>底面温度110℃を限度としてスチームなしでアイロン仕上げ可</li><li>石油系溶剤による弱いドライクリーニング可</li><li>REF：FNSK39FI3</li></ul>"
        },
        {
          "@type": "PropertyValue",
          "name": "activateEngraving",
          "value": false
        },
        {
          "@type": "PropertyValue",
          "name": "sellable",
          "value": true
        },
        {
          "@type": "PropertyValue",
          "name": "cscSellable",
          "value": true
        },
        {
          "@type": "PropertyValue",
          "name": "mom",
          "value": false
        },
        {
          "@type": "PropertyValue",
          "name": "locateInStore",
          "value": true
        },
        {
          "@type": "PropertyValue",
          "name": "materialGroupCode",
          "value": "Z05"
        },
        {
          "@type": "PropertyValue",
          "name": "filterCategories",
          "value": "Ready_To_Wear_Women"
        },
        {
          "@type": "PropertyValue",
          "name": "backOrderDisclaimer",
          "value": true
        },
        {
          "@type": "PropertyValue",
          "name": "backOrderFullDeposit",
          "value": false
        },
        {
          "@type": "PropertyValue",
          "name": "tryOnEnabled",
          "value": false
        },
        {
          "@type": "PropertyValue",
          "name": "isBundle",
          "value": false
        },
        {
          "@type": "PropertyValue",
          "name": "360ViewEnabled",
          "value": false
        }
      ],
      "category": [
        {
          "@type": "Thing",
          "url": "/jpn-jp/women/_/N-1q5sgib",
          "alternateName": "women",
          "name": "ウィメンズ",
          "identifier": "femme"
        },
        {
          "@type": "Thing",
          "url": "/jpn-jp/women/ready-to-wear/_/N-1nzqmbe",
          "alternateName": "ready-to-wear",
          "name": "プレタポルテ（洋服）",
          "identifier": "w-readytowear"
        },
        {
          "@type": "Thing",
          "url": "/jpn-jp/women/ready-to-wear/skirts-and-shorts/_/N-9pz88o",
          "alternateName": "skirts-and-shorts",
          "name": "ウィメンズ スカート＆ショートパンツ",
          "identifier": "w-skirts"
        }
      ],
      "disclaimers": {
        "value": "shipping_warning_bo",
        "popInContent": "global_backorder_info_popin_content",
        "popInTitle": "global_backorder_info_popin_title"
      },
      "color": "ブロン",
      "@context": "http://schema.org",
      "identifier": "1AAA0Q"
    }
  ],
  "disambiguatingDescription": "伝統的なテニススタイルをアップデートした、エレガントな「LV マッチ」コレクションに相応しいルック。タイムレスなポロシャツを柔らかで伸縮性のあるテクニカルジャージーで再解釈し、なめらかなコーティングを施したハーフファスナーでモダンなひねりを効かせました。プリーツを施した張りのあるミディアム丈のスカートが洗練された動きを演出し、鮮やかなバッグ「ループ」が今シーズンならではの遊び心をプラスします。",
  "_links": {
    "self": {
      "href": "/api/catalog/jpn-jp/product/nvprod3660093v"
    },
    "push": {
      "href": "/api/catalog/jpn-jp/product-push/nvprod3660093v"
    },
    "care-link": {
      "href": "/api/catalog/jpn-jp/care-link/nvprod3660093v"
    },
    "availability": {
      "href": "/api/catalog/jpn-jp/availability/nvprod3660093v"
    }
  },
  "@type": "Product",
  "sku": "nvsku3190004v",
  "isSimilarTo": [],
  "productTips": [],
  "url": "/jpn-jp/products/lv-match-look-03-nvprod3660093v",
  "accessoriesSKUs": [
    {
      "productVisible": true,
      "_links": {
        "look": {
          "href": "/api/catalog/jpn-jp/skus/M81484/look"
        },
        "parent": {
          "href": "/api/catalog/jpn-jp/product/nvprod3650044v"
        },
        "self": {
          "href": "/api/catalog/jpn-jp/product/M81484"
        },
        "perso-details": {
          "href": "/api/catalog/jpn-jp/skus/M81484/perso-detail"
        },
        "/api/rels/jpn-jp/add-to-cart-base/nvprod3650044v/M81484/1": {
          "name": "add-to-cart",
          "href": "/api/cart/jpn-jp"
        }
      },
      "macroColor": "イエロー",
      "@type": "ProductModel",
      "height": {
        "@type": "QuantitativeValue",
        "value": 13,
        "unitText": "cm"
      },
      "name": "ループ",
      "mainMaterial2": "VELVET",
      "width": {
        "@type": "QuantitativeValue",
        "value": 6,
        "unitText": "cm"
      },
      "offers": {
        "priceSpecification": {
          "priceCurrency": "JPY",
          "price": 309100
        },
        "@type": "Offer",
        "price": "¥309,100"
      },
      "disambiguatingDescription": "テニスボールのイエローを彷彿させる、鮮やかなイエローのモノグラム･ジャカード ベルベットで仕立てた「ループ」。ジャカードベロアは、リサイクルヤーンを織り上げた100％サステブルな素材です。",
      "image": [
        {
          "contentUrl": "https://jp.louisvuitton.com/images/is/image/lv/1/PP_VP_L/louis-vuitton-ループ--M81484_PM2_Front view.jpg?wid={IMG_WIDTH}&hei={IMG_HEIGHT}",
          "@type": "ImageObject",
          "name": "Front view",
          "@context": "http://schema.org"
        },
        {
          "contentUrl": "https://jp.louisvuitton.com/images/is/image/lv/1/PP_VP_L/louis-vuitton-ループ--M81484_PM1_Closeup view.jpg?wid={IMG_WIDTH}&hei={IMG_HEIGHT}",
          "@type": "ImageObject",
          "name": "Closeup view",
          "@context": "http://schema.org"
        },
        {
          "contentUrl": "https://jp.louisvuitton.com/images/is/image/lv/1/PP_VP_L/louis-vuitton-ループ--M81484_PM1_Side view.jpg?wid={IMG_WIDTH}&hei={IMG_HEIGHT}",
          "@type": "ImageObject",
          "name": "Side view",
          "@context": "http://schema.org"
        },
        {
          "contentUrl": "https://jp.louisvuitton.com/images/is/image/lv/1/PP_VP_L/louis-vuitton-ループ--M81484_PM1_Interior view.jpg?wid={IMG_WIDTH}&hei={IMG_HEIGHT}",
          "@type": "ImageObject",
          "name": "Interior view",
          "@context": "http://schema.org"
        },
        {
          "contentUrl": "https://jp.louisvuitton.com/images/is/image/lv/1/PP_VP_L/louis-vuitton-ループ--M81484_PM1_Detail view.jpg?wid={IMG_WIDTH}&hei={IMG_HEIGHT}",
          "@type": "ImageObject",
          "name": "Detail view",
          "@context": "http://schema.org"
        },
        {
          "contentUrl": "https://jp.louisvuitton.com/images/is/image/lv/1/PP_VP_L/louis-vuitton-ループ--M81484_PM1_Back view.jpg?wid={IMG_WIDTH}&hei={IMG_HEIGHT}",
          "@type": "ImageObject",
          "name": "Back view",
          "@context": "http://schema.org"
        }
      ],
      "url": "/jpn-jp/products/loop-nvprod3650044v",
      "material": "MONOGRAM VELOURS",
      "depth": {
        "@type": "QuantitativeValue",
        "value": 23,
        "unitText": "cm"
      },
      "highEndTemplate": false,
      "productId": "nvprod3650044v",
      "additionalProperty": [
        {
          "@type": "PropertyValue",
          "name": "colorIconURL",
          "value": "https://jp.louisvuitton.com/images/is/image/lv/1/LV/louis-vuitton--MKC-ACC-Jaune-fluo.jpg"
        },
        {
          "@type": "PropertyValue",
          "name": "detailedDescription",
          "value": "<ul><li>素材：モノグラム･ジャカード ベルベット</li><li>トリミング：レザー（皮革の種類：牛革）</li><li>ライニング：マイクロファイバー</li><li>金具（色：ゴールド）</li><li>フロントにファスナー式ポケット</li><li>ファスナー開閉式</li><li>ストラップ：取り外し可能, 調整可能</li><li>ストラップの頂点からバッグ上部までの長さ(最短)：35.0 cm</li><li>ストラップの頂点からバッグ上部までの長さ(最長)：50.0 cm</li><li>チェーン：取り外し可能</li><li>チェーンの頂点からバッグ上部までの長さ(最短)：25.0 cm</li></ul>"
        },
        {
          "@type": "PropertyValue",
          "name": "activateEngraving",
          "value": false
        },
        {
          "@type": "PropertyValue",
          "name": "sellable",
          "value": true
        },
        {
          "@type": "PropertyValue",
          "name": "cscSellable",
          "value": true
        },
        {
          "@type": "PropertyValue",
          "name": "mom",
          "value": false
        },
        {
          "@type": "PropertyValue",
          "name": "locateInStore",
          "value": true
        },
        {
          "@type": "PropertyValue",
          "name": "materialGroupCode",
          "value": "Z01"
        },
        {
          "@type": "PropertyValue",
          "name": "filterCategories",
          "value": "Leather_Goods_and_Accessories"
        },
        {
          "@type": "PropertyValue",
          "name": "backOrderDisclaimer",
          "value": true
        },
        {
          "@type": "PropertyValue",
          "name": "backOrderFullDeposit",
          "value": false
        },
        {
          "@type": "PropertyValue",
          "name": "tryOnEnabled",
          "value": false
        },
        {
          "@type": "PropertyValue",
          "name": "isBundle",
          "value": false
        },
        {
          "@type": "PropertyValue",
          "name": "360ViewEnabled",
          "value": false
        }
      ],
      "category": [
        {
          "@type": "Thing",
          "url": "/jpn-jp/women/_/N-1q5sgib",
          "alternateName": "women",
          "name": "ウィメンズ",
          "identifier": "femme"
        },
        {
          "@type": "Thing",
          "url": "/jpn-jp/women/handbags/_/N-tatseh",
          "alternateName": "handbags",
          "name": "バッグ",
          "identifier": "w-category-cat10070"
        },
        {
          "@type": "Thing",
          "url": "/jpn-jp/women/handbags/all-collections/_/N-iquzrc",
          "alternateName": "all-collections",
          "name": "All Collections",
          "identifier": "nvcat2600006v"
        }
      ],
      "disclaimers": {
        "value": "shipping_warning_bo",
        "popInContent": "global_backorder_info_popin_content",
        "popInTitle": "global_backorder_info_popin_title"
      },
      "color": "ジョーヌフルオ",
      "@context": "http://schema.org",
      "identifier": "M81484"
    }
  ],
  "category": [
    {
      "@type": "Thing",
      "url": "/jpn-jp/women/_/N-1q5sgib",
      "alternateName": "women",
      "name": "ウィメンズ",
      "identifier": "femme"
    },
    {
      "@type": "Thing",
      "url": "/jpn-jp/women/ready-to-wear/_/N-1nzqmbe",
      "alternateName": "ready-to-wear",
      "name": "プレタポルテ（洋服）",
      "identifier": "w-readytowear"
    },
    {
      "@type": "Thing",
      "url": "/jpn-jp/women/ready-to-wear/view-by-look/_/N-zazi08",
      "alternateName": "view-by-look",
      "name": "ルックブック",
      "identifier": "nvcat460115v"
    }
  ],
  "additionalProperty": [
    {
      "@type": "PropertyValue",
      "name": "hidePrice",
      "value": false
    },
    {
      "@type": "PropertyValue",
      "name": "subType",
      "value": "product"
    },
    {
      "@type": "PropertyValue",
      "name": "sizeGuide",
      "value": false
    }
  ],
  "name": "LV マッチ - LOOK 03",
  "isRelatedTo": [],
  "@context": "http://schema.org",
  "identifier": "nvprod3660093v"
}
